{
  "type": "Feature",
  "properties": {
    "gn:admin1_code":"00",
    "gn:asciiname":"L'Epineux",
    "gn:country_code":"MQ",
    "gn:dem":54,
    "gn:feature_class":"P",
    "gn:feature_code":"PPL",
    "gn:name":"L\u2019\u00c9pineux",
    "gn:population":0,
    "gn:timezone":"America/Martinique",
    "iso:country":"MQ",
    "name:fra_x_preferred":[
        "L\u2019\u00c9pineux"
    ],
    "wof:name":"L'Epineux",
    "wof:placetype":"locality"
},
  "geometry": {"coordinates":[-61.01331999999999,14.79542],"type":"Point"}
}