{
  "type": "Feature",
  "properties": {
    "gn:admin1_code":"MQ",
    "gn:admin2_code":"972.0",
    "gn:admin3_code":"9723.0",
    "gn:admin4_code":"97220.0",
    "gn:asciiname":"Bellevue",
    "gn:country_code":"MQ",
    "gn:dem":201,
    "gn:feature_class":"P",
    "gn:feature_code":"PPL",
    "gn:name":"Bellevue",
    "gn:population":0,
    "gn:timezone":"America/Martinique",
    "iso:country":"MQ",
    "name:fra_x_preferred":[
        "Bellevue"
    ],
    "name:und_x_variant":[
        "Quartier Bellevue"
    ],
    "wof:name":"Bellevue",
    "wof:placetype":"locality"
},
  "geometry": {"coordinates":[-60.88204,14.54339],"type":"Point"}
}