{
  "type": "Feature",
  "properties": {
    "gn:admin1_code":"MQ",
    "gn:admin2_code":"972.0",
    "gn:admin3_code":"9724.0",
    "gn:admin4_code":"97234.0",
    "gn:asciiname":"Fond Laillet",
    "gn:country_code":"MQ",
    "gn:dem":26,
    "gn:feature_class":"P",
    "gn:feature_code":"PPL",
    "gn:name":"Fond Laillet",
    "gn:population":0,
    "gn:timezone":"America/Martinique",
    "iso:country":"MQ",
    "wof:name":"Fond Laillet",
    "wof:placetype":"locality"
},
  "geometry": {"coordinates":[-61.15872,14.6673],"type":"Point"}
}