{
  "type": "Feature",
  "properties": {
    "gn:admin1_code":"00",
    "gn:asciiname":"Wam",
    "gn:country_code":"MQ",
    "gn:dem":270,
    "gn:feature_class":"P",
    "gn:feature_code":"PPL",
    "gn:name":"Wam",
    "gn:population":0,
    "gn:timezone":"America/Martinique",
    "iso:country":"MQ",
    "name:fra_x_preferred":[
        "Wam"
    ],
    "wof:name":"Wam",
    "wof:placetype":"locality"
},
  "geometry": {"coordinates":[-60.89325,14.54184],"type":"Point"}
}