{
  "type": "Feature",
  "properties": {
    "gn:admin1_code":"00",
    "gn:asciiname":"Vieille Citerne",
    "gn:country_code":"MQ",
    "gn:dem":260,
    "gn:feature_class":"P",
    "gn:feature_code":"PPL",
    "gn:name":"Vieille Citerne",
    "gn:population":0,
    "gn:timezone":"America/Martinique",
    "iso:country":"MQ",
    "name:fra_x_preferred":[
        "Vieille Citerne"
    ],
    "wof:name":"Vieille Citerne",
    "wof:placetype":"locality"
},
  "geometry": {"coordinates":[-60.89808000000001,14.5486],"type":"Point"}
}