{
  "type": "Feature",
  "properties": {
    "gn:admin1_code":"00",
    "gn:asciiname":"Longuet",
    "gn:country_code":"MQ",
    "gn:dem":159,
    "gn:feature_class":"P",
    "gn:feature_code":"PPL",
    "gn:name":"Longuet",
    "gn:population":0,
    "gn:timezone":"America/Martinique",
    "iso:country":"MQ",
    "name:deu_x_preferred":[
        "Longuet"
    ],
    "name:fra_x_preferred":[
        "Longuet"
    ],
    "name:jpn_x_preferred":[
        "\u30ed\u30f3\u30b2"
    ],
    "name:nds_x_preferred":[
        "Longuet"
    ],
    "name:rus_x_preferred":[
        "\u041b\u043e\u043d\u0433\u0435"
    ],
    "wof:name":"Longuet",
    "wof:placetype":"locality"
},
  "geometry": {"coordinates":[-61.05278000000001,14.48174],"type":"Point"}
}