{
  "type": "Feature",
  "properties": {
    "gn:admin1_code":"00",
    "gn:asciiname":"Longuet",
    "gn:country_code":"MQ",
    "gn:dem":159,
    "gn:feature_class":"P",
    "gn:feature_code":"PPL",
    "gn:name":"Longuet",
    "gn:population":0,
    "gn:timezone":"America/Martinique",
    "iso:country":"MQ",
    "name:fra_x_preferred":[
        "Longuet"
    ],
    "wof:name":"Longuet",
    "wof:placetype":"locality"
},
  "geometry": {"coordinates":[-61.05278000000001,14.48174],"type":"Point"}
}