{
  "type": "Feature",
  "properties": {
    "gn:admin1_code":"MQ",
    "gn:admin2_code":"972.0",
    "gn:admin3_code":"9722.0",
    "gn:admin4_code":"97201.0",
    "gn:asciiname":"Semaine",
    "gn:country_code":"MQ",
    "gn:dem":357,
    "gn:feature_class":"P",
    "gn:feature_code":"PPL",
    "gn:name":"Semaine",
    "gn:population":0,
    "gn:timezone":"America/Martinique",
    "iso:country":"MQ",
    "name:fra_x_preferred":[
        "Semaine"
    ],
    "name:und_x_variant":[
        "Quartier Semaine"
    ],
    "wof:name":"Semaine",
    "wof:placetype":"locality"
},
  "geometry": {"coordinates":[-61.1235,14.82016],"type":"Point"}
}