{
  "type": "Feature",
  "properties": {
    "gn:admin1_code":"MQ",
    "gn:admin2_code":"972.0",
    "gn:admin3_code":"9723.0",
    "gn:admin4_code":"97221.0",
    "gn:asciiname":"Guinee-Fleury",
    "gn:country_code":"MQ",
    "gn:dem":165,
    "gn:feature_class":"P",
    "gn:feature_code":"PPL",
    "gn:name":"Guin\u00e9e-Fleury",
    "gn:population":0,
    "gn:timezone":"America/Martinique",
    "iso:country":"MQ",
    "name:und_x_variant":[
        "Quartier la Fleury Guin\u00e9",
        "Quartier Fleury Guin\u00e9",
        "Guin\u00e9e-Fleury"
    ],
    "wof:name":"Guinee-Fleury",
    "wof:placetype":"locality"
},
  "geometry": {"coordinates":[-60.93301999999999,14.52549],"type":"Point"}
}