{
  "type": "Feature",
  "properties": {
    "gn:admin1_code":"MQ",
    "gn:admin2_code":"972.0",
    "gn:admin3_code":"9723.0",
    "gn:admin4_code":"97221.0",
    "gn:asciiname":"Lamberton",
    "gn:country_code":"MQ",
    "gn:dem":65,
    "gn:feature_class":"P",
    "gn:feature_code":"PPL",
    "gn:name":"Lamberton",
    "gn:population":0,
    "gn:timezone":"America/Martinique",
    "iso:country":"MQ",
    "name:deu_x_preferred":[
        "Lamberton"
    ],
    "name:fra_x_preferred":[
        "Lamberton"
    ],
    "name:ita_x_preferred":[
        "Lamberton"
    ],
    "name:pol_x_preferred":[
        "Lamberton"
    ],
    "name:rus_x_preferred":[
        "\u041b\u0430\u043c\u0431\u0435\u0440\u0442\u043e\u043d"
    ],
    "name:srp_x_preferred":[
        "\u041b\u0430\u043c\u0431\u0435\u0440\u0442\u043e\u043d"
    ],
    "name:vol_x_preferred":[
        "Lamberton"
    ],
    "wof:name":"Lamberton",
    "wof:placetype":"locality"
},
  "geometry": {"coordinates":[-60.95126,14.53819],"type":"Point"}
}