{
  "type": "Feature",
  "properties": {
    "gn:admin1_code":"MQ",
    "gn:admin2_code":"972.0",
    "gn:admin3_code":"9723.0",
    "gn:admin4_code":"97226.0",
    "gn:asciiname":"La Baie des Anglais",
    "gn:country_code":"MQ",
    "gn:dem":18,
    "gn:feature_class":"P",
    "gn:feature_code":"PPL",
    "gn:name":"La Baie des Anglais",
    "gn:population":0,
    "gn:timezone":"America/Martinique",
    "iso:country":"MQ",
    "name:fra_x_preferred":[
        "La Baie des Anglais"
    ],
    "wof:name":"La Baie des Anglais",
    "wof:placetype":"locality"
},
  "geometry": {"coordinates":[-60.85326,14.42154],"type":"Point"}
}