{
  "type": "Feature",
  "properties": {
    "gn:admin1_code":"00",
    "gn:asciiname":"Fonds Manoel",
    "gn:country_code":"MQ",
    "gn:dem":15,
    "gn:feature_class":"P",
    "gn:feature_code":"PPL",
    "gn:name":"Fonds Mano\u00ebl",
    "gn:population":0,
    "gn:timezone":"America/Martinique",
    "iso:country":"MQ",
    "name:fra_x_preferred":[
        "Fonds Mano\u00ebl"
    ],
    "wof:name":"Fonds Manoel",
    "wof:placetype":"locality"
},
  "geometry": {"coordinates":[-60.98639,14.49183],"type":"Point"}
}