{
  "type": "Feature",
  "properties": {
    "gn:admin1_code":"MQ",
    "gn:admin2_code":"972.0",
    "gn:admin3_code":"9721.0",
    "gn:admin4_code":"97224.0",
    "gn:asciiname":"Long Bois",
    "gn:country_code":"MQ",
    "gn:dem":171,
    "gn:feature_class":"P",
    "gn:feature_code":"PPL",
    "gn:name":"Long Bois",
    "gn:population":0,
    "gn:timezone":"America/Martinique",
    "iso:country":"MQ",
    "name:fra_x_preferred":[
        "Long Bois"
    ],
    "name:und_x_variant":[
        "Quartier Long Bois",
        "Long-Bois"
    ],
    "wof:name":"Long Bois",
    "wof:placetype":"locality"
},
  "geometry": {"coordinates":[-61.02686,14.66816],"type":"Point"}
}