{
  "type": "Feature",
  "properties": {
    "gn:admin1_code":"00",
    "gn:asciiname":"Constant",
    "gn:country_code":"MQ",
    "gn:dem":307,
    "gn:feature_class":"P",
    "gn:feature_code":"PPL",
    "gn:name":"Constant",
    "gn:population":0,
    "gn:timezone":"America/Martinique",
    "iso:country":"MQ",
    "name:cat_x_preferred":[
        "Constant"
    ],
    "name:ces_x_preferred":[
        "Constant"
    ],
    "name:deu_x_preferred":[
        "Constant"
    ],
    "name:fra_x_preferred":[
        "Constant"
    ],
    "name:ita_x_preferred":[
        "Constant"
    ],
    "name:jpn_x_preferred":[
        "\u5b9a\u6570"
    ],
    "name:nld_x_preferred":[
        "Constant"
    ],
    "name:spa_x_preferred":[
        "Constant"
    ],
    "name:tam_x_preferred":[
        "\u0bae\u0bbe\u0bb1\u0bbf\u0bb2\u0bbf"
    ],
    "name:ukr_x_preferred":[
        "\u041a\u043e\u043d\u0441\u0442\u0430\u043d"
    ],
    "wof:name":"Constant",
    "wof:placetype":"locality"
},
  "geometry": {"coordinates":[-61.02141999999999,14.5064],"type":"Point"}
}