{
  "type": "Feature",
  "properties": {
    "gn:admin1_code":"00",
    "gn:asciiname":"Constant",
    "gn:country_code":"MQ",
    "gn:dem":307,
    "gn:feature_class":"P",
    "gn:feature_code":"PPL",
    "gn:name":"Constant",
    "gn:population":0,
    "gn:timezone":"America/Martinique",
    "iso:country":"MQ",
    "name:fra_x_preferred":[
        "Constant"
    ],
    "wof:name":"Constant",
    "wof:placetype":"locality"
},
  "geometry": {"coordinates":[-61.02141999999999,14.5064],"type":"Point"}
}