{
  "type": "Feature",
  "properties": {
    "gn:admin1_code":"MQ",
    "gn:admin2_code":"972.0",
    "gn:admin3_code":"9723.0",
    "gn:admin4_code":"97207.0",
    "gn:asciiname":"Baringthon",
    "gn:country_code":"MQ",
    "gn:dem":68,
    "gn:feature_class":"P",
    "gn:feature_code":"PPL",
    "gn:name":"Baringthon",
    "gn:population":0,
    "gn:timezone":"America/Martinique",
    "iso:country":"MQ",
    "name:fra_x_preferred":[
        "Baringthon"
    ],
    "name:und_x_variant":[
        "Barington"
    ],
    "wof:name":"Baringthon",
    "wof:placetype":"locality"
},
  "geometry": {"coordinates":[-60.95871,14.55856],"type":"Point"}
}