{
  "type": "Feature",
  "properties": {
    "gn:admin1_code":"MQ",
    "gn:admin2_code":"972.0",
    "gn:admin3_code":"9723.0",
    "gn:admin4_code":"97226.0",
    "gn:asciiname":"Fond Repos",
    "gn:country_code":"MQ",
    "gn:dem":63,
    "gn:feature_class":"P",
    "gn:feature_code":"PPL",
    "gn:name":"Fond Repos",
    "gn:population":0,
    "gn:timezone":"America/Martinique",
    "iso:country":"MQ",
    "name:fra_x_preferred":[
        "Fond Repos"
    ],
    "wof:name":"Fond Repos",
    "wof:placetype":"locality"
},
  "geometry": {"coordinates":[-60.83691999999999,14.45593],"type":"Point"}
}