{
  "type": "Feature",
  "properties": {
    "gn:admin1_code":"MQ",
    "gn:admin2_code":"972.0",
    "gn:admin3_code":"9723.0",
    "gn:admin4_code":"97207.0",
    "gn:asciiname":"La Manzo",
    "gn:country_code":"MQ",
    "gn:dem":56,
    "gn:feature_class":"P",
    "gn:feature_code":"PPL",
    "gn:name":"La Manzo",
    "gn:population":0,
    "gn:timezone":"America/Martinique",
    "iso:country":"MQ",
    "name:und_x_variant":[
        "Quartier la Manzo",
        "La Manzo"
    ],
    "wof:name":"La Manzo",
    "wof:placetype":"locality"
},
  "geometry": {"coordinates":[-60.93349,14.58784],"type":"Point"}
}