{
  "type": "Feature",
  "properties": {
    "gn:admin1_code":"MQ",
    "gn:admin2_code":"972.0",
    "gn:admin3_code":"9723.0",
    "gn:admin4_code":"97227.0",
    "gn:asciiname":"Corps de Garde",
    "gn:country_code":"MQ",
    "gn:dem":141,
    "gn:feature_class":"P",
    "gn:feature_code":"PPL",
    "gn:name":"Corps de Garde",
    "gn:population":0,
    "gn:timezone":"America/Martinique",
    "iso:country":"MQ",
    "name:und_x_variant":[
        "Quartier Corps de Garde",
        "Corps de Garde"
    ],
    "wof:name":"Corps de Garde",
    "wof:placetype":"locality"
},
  "geometry": {"coordinates":[-60.94001,14.47432],"type":"Point"}
}