{
  "type": "Feature",
  "properties": {
    "gn:admin1_code":"MQ",
    "gn:admin2_code":"972.0",
    "gn:admin3_code":"9723.0",
    "gn:admin4_code":"97232.0",
    "gn:asciiname":"Petit Campeche",
    "gn:country_code":"MQ",
    "gn:dem":138,
    "gn:feature_class":"P",
    "gn:feature_code":"PPL",
    "gn:name":"Petit Camp\u00eache",
    "gn:population":0,
    "gn:timezone":"America/Martinique",
    "iso:country":"MQ",
    "name:und_x_variant":[
        "Quartier Petit Camp\u00eache",
        "Petit Camp\u00eache"
    ],
    "wof:name":"Petit Campeche",
    "wof:placetype":"locality"
},
  "geometry": {"coordinates":[-60.85634,14.52968],"type":"Point"}
}