{
  "type": "Feature",
  "properties": {
    "gn:admin1_code":"MQ",
    "gn:admin2_code":"972.0",
    "gn:admin3_code":"9723.0",
    "gn:admin4_code":"97221.0",
    "gn:asciiname":"Beausejour",
    "gn:country_code":"MQ",
    "gn:dem":78,
    "gn:feature_class":"P",
    "gn:feature_code":"PPL",
    "gn:name":"Beaus\u00e9jour",
    "gn:population":0,
    "gn:timezone":"America/Martinique",
    "iso:country":"MQ",
    "name:ara_x_preferred":[
        "\u0628\u0648\u0633\u064a\u062c\u0648\u0631"
    ],
    "name:deu_x_preferred":[
        "Beaus\u00e9jour"
    ],
    "name:fra_x_preferred":[
        "Beaus\u00e9jour"
    ],
    "name:slv_x_preferred":[
        "Beausejour"
    ],
    "name:spa_x_preferred":[
        "Beaus\u00e9jour"
    ],
    "wof:name":"Beausejour",
    "wof:placetype":"locality"
},
  "geometry": {"coordinates":[-60.92466,14.55016],"type":"Point"}
}