{
  "type": "Feature",
  "properties": {
    "gn:admin1_code":"MQ",
    "gn:asciiname":"La Huvet",
    "gn:country_code":"MQ",
    "gn:dem":128,
    "gn:feature_class":"P",
    "gn:feature_code":"PPL",
    "gn:name":"La Huvet",
    "gn:population":0,
    "gn:timezone":"America/Martinique",
    "iso:country":"MQ",
    "name:fra_x_preferred":[
        "La Huvet"
    ],
    "wof:name":"La Huvet",
    "wof:placetype":"locality"
},
  "geometry": {"coordinates":[-60.85681999999999,14.49145],"type":"Point"}
}