{
  "type": "Feature",
  "properties": {
    "gn:admin1_code":"00",
    "gn:asciiname":"Robin",
    "gn:country_code":"MQ",
    "gn:dem":237,
    "gn:feature_class":"P",
    "gn:feature_code":"PPL",
    "gn:name":"Robin",
    "gn:population":0,
    "gn:timezone":"America/Martinique",
    "iso:country":"MQ",
    "name:fra_x_preferred":[
        "Robin"
    ],
    "wof:name":"Robin",
    "wof:placetype":"locality"
},
  "geometry": {"coordinates":[-61.03039,14.78905],"type":"Point"}
}