{
  "type": "Feature",
  "properties": {
    "gn:admin1_code":"00",
    "gn:asciiname":"Robin",
    "gn:country_code":"MQ",
    "gn:dem":237,
    "gn:feature_class":"P",
    "gn:feature_code":"PPL",
    "gn:name":"Robin",
    "gn:population":0,
    "gn:timezone":"America/Martinique",
    "iso:country":"MQ",
    "name:bul_x_preferred":[
        "\u0420\u043e\u0431\u0438\u043d"
    ],
    "name:dan_x_preferred":[
        "Robin"
    ],
    "name:deu_x_preferred":[
        "Robin"
    ],
    "name:fin_x_preferred":[
        "Robin"
    ],
    "name:fra_x_preferred":[
        "Robin"
    ],
    "name:ind_x_preferred":[
        "Robin"
    ],
    "name:ita_x_preferred":[
        "Robin"
    ],
    "name:jpn_x_preferred":[
        "\u30ed\u30d3\u30f3"
    ],
    "name:nld_x_preferred":[
        "Robin"
    ],
    "name:pol_x_preferred":[
        "Robin"
    ],
    "name:por_x_preferred":[
        "Robin"
    ],
    "name:rus_x_preferred":[
        "\u0420\u043e\u0431\u0438\u043d"
    ],
    "name:spa_x_preferred":[
        "Robin"
    ],
    "name:tam_x_preferred":[
        "\u0bb0\u0bbe\u0baa\u0bbf\u0ba9\u0bcd"
    ],
    "name:tgl_x_preferred":[
        "Robin"
    ],
    "name:vie_x_preferred":[
        "Robin"
    ],
    "wof:name":"Robin",
    "wof:placetype":"locality"
},
  "geometry": {"coordinates":[-61.03039,14.78905],"type":"Point"}
}