{
  "type": "Feature",
  "properties": {
    "gn:admin1_code":"MQ",
    "gn:admin2_code":"972.0",
    "gn:admin3_code":"9724.0",
    "gn:admin4_code":"97204.0",
    "gn:asciiname":"La Dessaint",
    "gn:country_code":"MQ",
    "gn:dem":56,
    "gn:feature_class":"P",
    "gn:feature_code":"PPL",
    "gn:name":"La Dessaint",
    "gn:population":0,
    "gn:timezone":"America/Martinique",
    "iso:country":"MQ",
    "wof:name":"La Dessaint",
    "wof:placetype":"locality"
},
  "geometry": {"coordinates":[-61.18169,14.71802],"type":"Point"}
}