{
  "type": "Feature",
  "properties": {
    "gn:admin1_code":"00",
    "gn:asciiname":"Boulevard",
    "gn:country_code":"MQ",
    "gn:dem":50,
    "gn:feature_class":"P",
    "gn:feature_code":"PPL",
    "gn:name":"Boulevard",
    "gn:population":0,
    "gn:timezone":"America/Martinique",
    "iso:country":"MQ",
    "name:fra_x_preferred":[
        "Boulevard"
    ],
    "wof:name":"Boulevard",
    "wof:placetype":"locality"
},
  "geometry": {"coordinates":[-60.9619,14.53298],"type":"Point"}
}