{
  "type": "Feature",
  "properties": {
    "gn:admin1_code":"00",
    "gn:asciiname":"Boulevard",
    "gn:country_code":"MQ",
    "gn:dem":50,
    "gn:feature_class":"P",
    "gn:feature_code":"PPL",
    "gn:name":"Boulevard",
    "gn:population":0,
    "gn:timezone":"America/Martinique",
    "iso:country":"MQ",
    "name:ara_x_preferred":[
        "\u0628\u0648\u0644\u0641\u0627\u0631"
    ],
    "name:aze_x_preferred":[
        "Bulvar"
    ],
    "name:bel_x_preferred":[
        "\u0411\u0443\u043b\u044c\u0432\u0430\u0440"
    ],
    "name:bul_x_preferred":[
        "\u0411\u0443\u043b\u0435\u0432\u0430\u0440\u0434"
    ],
    "name:cat_x_preferred":[
        "Bulevard"
    ],
    "name:ces_x_preferred":[
        "Bulv\u00e1r"
    ],
    "name:dan_x_preferred":[
        "Boulevard"
    ],
    "name:deu_x_preferred":[
        "Boulevard"
    ],
    "name:epo_x_preferred":[
        "Bulvardo"
    ],
    "name:est_x_preferred":[
        "Bulvar"
    ],
    "name:fas_x_preferred":[
        "\u0628\u0644\u0648\u0627\u0631"
    ],
    "name:fin_x_preferred":[
        "Bulevardi"
    ],
    "name:fra_x_preferred":[
        "Boulevard"
    ],
    "name:heb_x_preferred":[
        "\u05e9\u05d3\u05e8\u05d4"
    ],
    "name:hrv_x_preferred":[
        "Avenija"
    ],
    "name:ido_x_preferred":[
        "Bulvardo"
    ],
    "name:ind_x_preferred":[
        "Adimarga"
    ],
    "name:ita_x_preferred":[
        "Boulevard"
    ],
    "name:jpn_x_preferred":[
        "\u30d6\u30fc\u30eb\u30d0\u30fc\u30eb"
    ],
    "name:kaz_x_preferred":[
        "\u0411\u0443\u043b\u044c\u0432\u0430\u0440"
    ],
    "name:kor_x_preferred":[
        "\ubd88\ubc14\ub974"
    ],
    "name:nld_x_preferred":[
        "Boulevard"
    ],
    "name:nor_x_preferred":[
        "Bulevard"
    ],
    "name:pol_x_preferred":[
        "Bulwar"
    ],
    "name:por_x_preferred":[
        "Boulevard"
    ],
    "name:ron_x_preferred":[
        "Bulevard"
    ],
    "name:rus_x_preferred":[
        "\u0411\u0443\u043b\u044c\u0432\u0430\u0440"
    ],
    "name:slk_x_preferred":[
        "Bulv\u00e1r"
    ],
    "name:spa_x_preferred":[
        "Bulevar"
    ],
    "name:srp_x_preferred":[
        "\u0411\u0443\u043b\u0435\u0432\u0430\u0440"
    ],
    "name:swe_x_preferred":[
        "Boulevard"
    ],
    "name:tur_x_preferred":[
        "Bulvar"
    ],
    "name:ukr_x_preferred":[
        "\u0411\u0443\u043b\u044c\u0432\u0430\u0440"
    ],
    "name:vie_x_preferred":[
        "\u0110\u1ea1i l\u1ed9"
    ],
    "wof:name":"Boulevard",
    "wof:placetype":"locality"
},
  "geometry": {"coordinates":[-60.9619,14.53298],"type":"Point"}
}