{
  "type": "Feature",
  "properties": {
    "gn:admin1_code":"MQ",
    "gn:admin2_code":"972.0",
    "gn:admin3_code":"9724.0",
    "gn:admin4_code":"97208.0",
    "gn:asciiname":"Quartier Bedzy",
    "gn:country_code":"MQ",
    "gn:dem":324,
    "gn:feature_class":"P",
    "gn:feature_code":"PPL",
    "gn:name":"Quartier Bedzy",
    "gn:population":0,
    "gn:timezone":"America/Martinique",
    "iso:country":"MQ",
    "wof:name":"Quartier Bedzy",
    "wof:placetype":"locality"
},
  "geometry": {"coordinates":[-61.14283,14.72691],"type":"Point"}
}