{
  "type": "Feature",
  "properties": {
    "gn:admin1_code":"00",
    "gn:asciiname":"Morne Pavillon",
    "gn:country_code":"MQ",
    "gn:dem":291,
    "gn:feature_class":"P",
    "gn:feature_code":"PPL",
    "gn:name":"Morne Pavillon",
    "gn:population":0,
    "gn:timezone":"America/Martinique",
    "iso:country":"MQ",
    "name:fra_x_preferred":[
        "Morne Pavillon"
    ],
    "wof:name":"Morne Pavillon",
    "wof:placetype":"locality"
},
  "geometry": {"coordinates":[-61.01617,14.49778],"type":"Point"}
}