{
  "type": "Feature",
  "properties": {
    "gn:admin1_code":"MQ",
    "gn:admin2_code":"972.0",
    "gn:admin3_code":"9723.0",
    "gn:admin4_code":"97227.0",
    "gn:asciiname":"Montravail",
    "gn:country_code":"MQ",
    "gn:dem":205,
    "gn:feature_class":"P",
    "gn:feature_code":"PPL",
    "gn:name":"Montravail",
    "gn:population":0,
    "gn:timezone":"America/Martinique",
    "iso:country":"MQ",
    "name:und_x_variant":[
        "Quartier Montravail",
        "Montravail"
    ],
    "wof:name":"Montravail",
    "wof:placetype":"locality"
},
  "geometry": {"coordinates":[-60.93389000000001,14.49444],"type":"Point"}
}