{
  "type": "Feature",
  "properties": {
    "gn:admin1_code":"00",
    "gn:asciiname":"Brisse",
    "gn:country_code":"MQ",
    "gn:dem":203,
    "gn:feature_class":"P",
    "gn:feature_code":"PPL",
    "gn:name":"Brisse",
    "gn:population":0,
    "gn:timezone":"America/Martinique",
    "iso:country":"MQ",
    "name:fra_x_preferred":[
        "Brisse"
    ],
    "wof:name":"Brisse",
    "wof:placetype":"locality"
},
  "geometry": {"coordinates":[-60.96661,14.68901],"type":"Point"}
}