{
  "type": "Feature",
  "properties": {
    "gn:admin1_code":"MQ",
    "gn:asciiname":"Gaalon",
    "gn:country_code":"MQ",
    "gn:dem":46,
    "gn:feature_class":"P",
    "gn:feature_code":"PPL",
    "gn:name":"Gaalon",
    "gn:population":0,
    "gn:timezone":"America/Martinique",
    "iso:country":"MQ",
    "name:fra_x_preferred":[
        "Gaalon"
    ],
    "wof:name":"Gaalon",
    "wof:placetype":"locality"
},
  "geometry": {"coordinates":[-60.88942,14.66431],"type":"Point"}
}