{
  "type": "Feature",
  "properties": {
    "gn:admin1_code":"00",
    "gn:asciiname":"Mont Vert",
    "gn:country_code":"MQ",
    "gn:dem":138,
    "gn:feature_class":"P",
    "gn:feature_code":"PPL",
    "gn:name":"Mont Vert",
    "gn:population":0,
    "gn:timezone":"America/Martinique",
    "iso:country":"MQ",
    "name:fra_x_preferred":[
        "Mont Vert"
    ],
    "wof:name":"Mont Vert",
    "wof:placetype":"locality"
},
  "geometry": {"coordinates":[-60.95329,14.68984],"type":"Point"}
}