{
  "type": "Feature",
  "properties": {
    "gn:admin1_code":"00",
    "gn:asciiname":"Riviere Roche",
    "gn:country_code":"MQ",
    "gn:dem":134,
    "gn:feature_class":"P",
    "gn:feature_code":"PPL",
    "gn:name":"Rivi\u00e8re Roche",
    "gn:population":0,
    "gn:timezone":"America/Martinique",
    "iso:country":"MQ",
    "name:fra_x_preferred":[
        "Rivi\u00e8re Roche"
    ],
    "wof:name":"Riviere Roche",
    "wof:placetype":"locality"
},
  "geometry": {"coordinates":[-61.01538000000001,14.68278],"type":"Point"}
}