{
  "type": "Feature",
  "properties": {
    "gn:admin1_code":"00",
    "gn:asciiname":"Macabou",
    "gn:country_code":"MQ",
    "gn:dem":16,
    "gn:feature_class":"P",
    "gn:feature_code":"PPL",
    "gn:name":"Macabou",
    "gn:population":0,
    "gn:timezone":"America/Martinique",
    "iso:country":"MQ",
    "name:fra_x_preferred":[
        "Macabou"
    ],
    "wof:name":"Macabou",
    "wof:placetype":"locality"
},
  "geometry": {"coordinates":[-60.82488000000001,14.51051],"type":"Point"}
}