{
  "type": "Feature",
  "properties": {
    "gn:admin1_code":"00",
    "gn:asciiname":"Pavillon",
    "gn:country_code":"MQ",
    "gn:dem":27,
    "gn:feature_class":"P",
    "gn:feature_code":"PPL",
    "gn:name":"Pavillon",
    "gn:population":0,
    "gn:timezone":"America/Martinique",
    "iso:country":"MQ",
    "name:deu_x_preferred":[
        "Pavillon"
    ],
    "name:fra_x_preferred":[
        "Pavillon"
    ],
    "name:ltz_x_preferred":[
        "Pavillon"
    ],
    "wof:name":"Pavillon",
    "wof:placetype":"locality"
},
  "geometry": {"coordinates":[-60.92434,14.4702],"type":"Point"}
}