{
  "type": "Feature",
  "properties": {
    "gn:admin1_code":"00",
    "gn:asciiname":"Chapelle",
    "gn:country_code":"MQ",
    "gn:dem":145,
    "gn:feature_class":"P",
    "gn:feature_code":"PPL",
    "gn:name":"Chapelle",
    "gn:population":0,
    "gn:timezone":"America/Martinique",
    "iso:country":"MQ",
    "name:bre_x_preferred":[
        "Chapelle"
    ],
    "name:deu_x_preferred":[
        "Chapelle"
    ],
    "name:epo_x_preferred":[
        "Chapelle"
    ],
    "name:fra_x_preferred":[
        "Chapelle"
    ],
    "name:heb_x_preferred":[
        "\u05e9\u05d0\u05e4\u05dc"
    ],
    "name:ita_x_preferred":[
        "Chapelle"
    ],
    "name:jpn_x_preferred":[
        "\u30b7\u30e3\u30da\u30eb"
    ],
    "name:nld_x_preferred":[
        "Chapelle"
    ],
    "name:pol_x_preferred":[
        "Chapelle"
    ],
    "name:ron_x_preferred":[
        "Chapelle"
    ],
    "name:rus_x_preferred":[
        "\u0428\u0430\u043f\u0435\u043b\u044c"
    ],
    "name:srp_x_preferred":[
        "\u0428\u0430\u043f\u0435\u043b"
    ],
    "name:swe_x_preferred":[
        "Chapelle"
    ],
    "wof:name":"Chapelle",
    "wof:placetype":"locality"
},
  "geometry": {"coordinates":[-61.06385,14.53144],"type":"Point"}
}