{
  "type": "Feature",
  "properties": {
    "gn:admin1_code":"00",
    "gn:asciiname":"Chapelle",
    "gn:country_code":"MQ",
    "gn:dem":145,
    "gn:feature_class":"P",
    "gn:feature_code":"PPL",
    "gn:name":"Chapelle",
    "gn:population":0,
    "gn:timezone":"America/Martinique",
    "iso:country":"MQ",
    "name:fra_x_preferred":[
        "Chapelle"
    ],
    "wof:name":"Chapelle",
    "wof:placetype":"locality"
},
  "geometry": {"coordinates":[-61.06385,14.53144],"type":"Point"}
}