{
  "type": "Feature",
  "properties": {
    "gn:admin1_code":"MQ",
    "gn:admin2_code":"972.0",
    "gn:admin3_code":"9724.0",
    "gn:admin4_code":"97234.0",
    "gn:asciiname":"Bellefontaine",
    "gn:country_code":"MQ",
    "gn:dem":10,
    "gn:feature_class":"P",
    "gn:feature_code":"PPL",
    "gn:name":"Bellefontaine",
    "gn:population":0,
    "gn:timezone":"America/Martinique",
    "iso:country":"MQ",
    "name:ceb_x_preferred":[
        "Bellefontaine"
    ],
    "name:deu_x_preferred":[
        "Bellefontaine"
    ],
    "name:epo_x_preferred":[
        "Bellefontaine"
    ],
    "name:fra_x_historical":[
        "Fond Belle Fontaine"
    ],
    "name:fra_x_preferred":[
        "Fond Belle Fontaine"
    ],
    "name:fra_x_variant":[
        "Bellefontaine"
    ],
    "name:ita_x_preferred":[
        "Bellefontaine"
    ],
    "name:nds_x_preferred":[
        "Bellefontaine"
    ],
    "name:nld_x_preferred":[
        "Bellefontaine"
    ],
    "name:oci_x_preferred":[
        "Bellefontaine"
    ],
    "name:pms_x_preferred":[
        "Bellefontaine"
    ],
    "name:pol_x_preferred":[
        "Bellefontaine"
    ],
    "name:por_x_preferred":[
        "Bellefontaine"
    ],
    "name:slk_x_preferred":[
        "Bellefontaine"
    ],
    "name:spa_x_preferred":[
        "Bellefontaine"
    ],
    "name:srp_x_preferred":[
        "\u0411\u0435\u043b\u0444\u043e\u043d\u0442\u0435\u043d"
    ],
    "name:swe_x_preferred":[
        "Bellefontaine"
    ],
    "name:ukr_x_preferred":[
        "\u0411\u0435\u043b\u044c\u0444\u043e\u043d\u0442\u0435\u043d"
    ],
    "name:zho_x_preferred":[
        "\u8d1d\u52d2\u4e30\u5766"
    ],
    "wof:name":"Bellefontaine",
    "wof:placetype":"locality"
},
  "geometry": {"coordinates":[-61.16402,14.67311],"type":"Point"}
}