{
  "type": "Feature",
  "properties": {
    "gn:admin1_code":"MQ",
    "gn:admin2_code":"972.0",
    "gn:admin3_code":"9724.0",
    "gn:admin4_code":"97234.0",
    "gn:asciiname":"Bellefontaine",
    "gn:country_code":"MQ",
    "gn:dem":10,
    "gn:feature_class":"P",
    "gn:feature_code":"PPL",
    "gn:name":"Bellefontaine",
    "gn:population":0,
    "gn:timezone":"America/Martinique",
    "iso:country":"MQ",
    "name:fra_x_historical":[
        "Fond Belle Fontaine"
    ],
    "name:fra_x_preferred":[
        "Fond Belle Fontaine"
    ],
    "wof:name":"Bellefontaine",
    "wof:placetype":"locality"
},
  "geometry": {"coordinates":[-61.16402,14.67311],"type":"Point"}
}