{
  "type": "Feature",
  "properties": {
    "gn:admin1_code":"00",
    "gn:asciiname":"Morne Vaudin",
    "gn:country_code":"MQ",
    "gn:dem":169,
    "gn:feature_class":"P",
    "gn:feature_code":"PPL",
    "gn:name":"Morne Vaudin",
    "gn:population":0,
    "gn:timezone":"America/Martinique",
    "iso:country":"MQ",
    "name:fra_x_preferred":[
        "Morne Vaudin"
    ],
    "wof:name":"Morne Vaudin",
    "wof:placetype":"locality"
},
  "geometry": {"coordinates":[-61.02591,14.70524],"type":"Point"}
}