{
  "type": "Feature",
  "properties": {
    "gn:admin1_code":"00",
    "gn:asciiname":"Bas Mangots",
    "gn:country_code":"MQ",
    "gn:dem":91,
    "gn:feature_class":"P",
    "gn:feature_code":"PPL",
    "gn:name":"Bas Mangots",
    "gn:population":0,
    "gn:timezone":"America/Martinique",
    "iso:country":"MQ",
    "name:fra_x_preferred":[
        "Bas Mangots"
    ],
    "wof:name":"Bas Mangots",
    "wof:placetype":"locality"
},
  "geometry": {"coordinates":[-60.89426,14.48073],"type":"Point"}
}