{
  "type": "Feature",
  "properties": {
    "gn:admin1_code":"00",
    "gn:asciiname":"Fond Clemence",
    "gn:country_code":"MQ",
    "gn:dem":123,
    "gn:feature_class":"P",
    "gn:feature_code":"PPL",
    "gn:name":"Fond Cl\u00e9mence",
    "gn:population":0,
    "gn:timezone":"America/Martinique",
    "iso:country":"MQ",
    "name:fra_x_preferred":[
        "Fond Cl\u00e9mence"
    ],
    "wof:name":"Fond Clemence",
    "wof:placetype":"locality"
},
  "geometry": {"coordinates":[-61.0229,14.78952],"type":"Point"}
}