{
  "type": "Feature",
  "properties": {
    "gn:admin1_code":"MQ",
    "gn:admin2_code":"972.0",
    "gn:admin3_code":"9722.0",
    "gn:admin4_code":"97212.0",
    "gn:asciiname":"Birot",
    "gn:country_code":"MQ",
    "gn:dem":103,
    "gn:feature_class":"P",
    "gn:feature_code":"PPL",
    "gn:name":"Birot",
    "gn:population":0,
    "gn:timezone":"America/Martinique",
    "iso:country":"MQ",
    "name:und_x_variant":[
        "Quartier Birot",
        "Birot"
    ],
    "wof:name":"Birot",
    "wof:placetype":"locality"
},
  "geometry": {"coordinates":[-60.98849000000001,14.71722],"type":"Point"}
}