{
  "type": "Feature",
  "properties": {
    "gn:admin1_code":"MQ",
    "gn:admin2_code":"972.0",
    "gn:admin3_code":"9723.0",
    "gn:admin4_code":"97210.0",
    "gn:asciiname":"Petite Gamelle",
    "gn:country_code":"MQ",
    "gn:dem":78,
    "gn:feature_class":"P",
    "gn:feature_code":"PPL",
    "gn:name":"Petite Gamelle",
    "gn:population":0,
    "gn:timezone":"America/Martinique",
    "iso:country":"MQ",
    "name:fra_x_preferred":[
        "Petite Gamelle"
    ],
    "wof:name":"Petite Gamelle",
    "wof:placetype":"locality"
},
  "geometry": {"coordinates":[-60.928,14.59647],"type":"Point"}
}