{
  "type": "Feature",
  "properties": {
    "gn:admin1_code":"MQ",
    "gn:admin2_code":"972.0",
    "gn:admin3_code":"9722.0",
    "gn:admin4_code":"97212.0",
    "gn:asciiname":"Grozan",
    "gn:country_code":"MQ",
    "gn:dem":221,
    "gn:feature_class":"P",
    "gn:feature_code":"PPL",
    "gn:name":"Grozan",
    "gn:population":0,
    "gn:timezone":"America/Martinique",
    "iso:country":"MQ",
    "name:fra_x_preferred":[
        "Grozan"
    ],
    "name:und_x_variant":[
        "Quartier Grosan"
    ],
    "wof:name":"Grozan",
    "wof:placetype":"locality"
},
  "geometry": {"coordinates":[-60.98886,14.69767],"type":"Point"}
}