{
  "type": "Feature",
  "properties": {
    "gn:admin1_code":"MQ",
    "gn:admin2_code":"972.0",
    "gn:admin3_code":"9721.0",
    "gn:admin4_code":"97213.0",
    "gn:asciiname":"Sabine",
    "gn:country_code":"MQ",
    "gn:dem":142,
    "gn:feature_class":"P",
    "gn:feature_code":"PPL",
    "gn:name":"Sabine",
    "gn:population":0,
    "gn:timezone":"America/Martinique",
    "iso:country":"MQ",
    "name:fra_x_preferred":[
        "Sabine"
    ],
    "name:und_x_variant":[
        "Quartier la Sabine"
    ],
    "wof:name":"Sabine",
    "wof:placetype":"locality"
},
  "geometry": {"coordinates":[-60.97957,14.67412],"type":"Point"}
}