{
  "type": "Feature",
  "properties": {
    "gn:admin1_code":"00",
    "gn:asciiname":"Bois Coupe",
    "gn:country_code":"MQ",
    "gn:dem":89,
    "gn:feature_class":"P",
    "gn:feature_code":"PPL",
    "gn:name":"Bois Coup\u00e9",
    "gn:population":0,
    "gn:timezone":"America/Martinique",
    "iso:country":"MQ",
    "name:fra_x_preferred":[
        "Bois Coup\u00e9"
    ],
    "wof:name":"Bois Coupe",
    "wof:placetype":"locality"
},
  "geometry": {"coordinates":[-61.05333,14.52342],"type":"Point"}
}