{
  "type": "Feature",
  "properties": {
    "gn:admin1_code":"MQ",
    "gn:admin2_code":"972.0",
    "gn:admin3_code":"9722.0",
    "gn:admin4_code":"97230.0",
    "gn:asciiname":"Desforts",
    "gn:country_code":"MQ",
    "gn:dem":118,
    "gn:feature_class":"P",
    "gn:feature_code":"PPL",
    "gn:name":"Desforts",
    "gn:population":0,
    "gn:timezone":"America/Martinique",
    "iso:country":"MQ",
    "name:und_x_variant":[
        "Quartier Desforts",
        "Desforts"
    ],
    "wof:name":"Desforts",
    "wof:placetype":"locality"
},
  "geometry": {"coordinates":[-60.97185,14.71757],"type":"Point"}
}