{
  "type": "Feature",
  "properties": {
    "gn:admin1_code":"MQ",
    "gn:admin2_code":"972.0",
    "gn:admin3_code":"9722.0",
    "gn:admin4_code":"97230.0",
    "gn:asciiname":"Ferre",
    "gn:country_code":"MQ",
    "gn:dem":20,
    "gn:feature_class":"P",
    "gn:feature_code":"PPL",
    "gn:name":"Ferr\u00e9",
    "gn:population":0,
    "gn:timezone":"America/Martinique",
    "iso:country":"MQ",
    "name:deu_x_preferred":[
        "Ferre"
    ],
    "name:fra_x_preferred":[
        "Ferr\u00e9"
    ],
    "name:spa_x_preferred":[
        "Ferre"
    ],
    "name:und_x_variant":[
        "Ferret"
    ],
    "wof:name":"Ferre",
    "wof:placetype":"locality"
},
  "geometry": {"coordinates":[-60.89675,14.74777],"type":"Point"}
}