{
  "type": "Feature",
  "properties": {
    "gn:admin1_code":"00",
    "gn:asciiname":"Belfond",
    "gn:country_code":"MQ",
    "gn:dem":47,
    "gn:feature_class":"P",
    "gn:feature_code":"PPL",
    "gn:name":"Belfond",
    "gn:population":0,
    "gn:timezone":"America/Martinique",
    "iso:country":"MQ",
    "name:fra_x_preferred":[
        "Belfond"
    ],
    "wof:name":"Belfond",
    "wof:placetype":"locality"
},
  "geometry": {"coordinates":[-60.86891,14.43906],"type":"Point"}
}