{
  "type": "Feature",
  "properties": {
    "gn:admin1_code":"MQ",
    "gn:admin2_code":"972.0",
    "gn:admin3_code":"9722.0",
    "gn:admin4_code":"97228.0",
    "gn:asciiname":"Ferme Saint-Jacques",
    "gn:country_code":"MQ",
    "gn:dem":74,
    "gn:feature_class":"P",
    "gn:feature_code":"PPL",
    "gn:name":"Ferme Saint-Jacques",
    "gn:population":0,
    "gn:timezone":"America/Martinique",
    "iso:country":"MQ",
    "wof:name":"Ferme Saint-Jacques",
    "wof:placetype":"locality"
},
  "geometry": {"coordinates":[-61.01704,14.79332],"type":"Point"}
}