{
  "type": "Feature",
  "properties": {
    "gn:admin1_code":"00",
    "gn:asciiname":"Jacques",
    "gn:country_code":"MQ",
    "gn:dem":203,
    "gn:feature_class":"P",
    "gn:feature_code":"PPL",
    "gn:name":"Jacques",
    "gn:population":0,
    "gn:timezone":"America/Martinique",
    "iso:country":"MQ",
    "name:deu_x_preferred":[
        "Jacques"
    ],
    "name:eus_x_preferred":[
        "Jakue"
    ],
    "name:fas_x_preferred":[
        "\u0698\u0627\u06a9"
    ],
    "name:fra_x_preferred":[
        "Jacques"
    ],
    "name:nor_x_preferred":[
        "Jacques"
    ],
    "name:rus_x_preferred":[
        "\u0416\u0430\u043a"
    ],
    "name:ukr_x_preferred":[
        "\u0416\u0430\u043a"
    ],
    "wof:name":"Jacques",
    "wof:placetype":"locality"
},
  "geometry": {"coordinates":[-60.92328000000001,14.48523],"type":"Point"}
}