{
  "type": "Feature",
  "properties": {
    "gn:admin1_code":"MQ",
    "gn:admin2_code":"972.0",
    "gn:admin3_code":"9724.0",
    "gn:admin4_code":"97205.0",
    "gn:asciiname":"Morne Vente",
    "gn:country_code":"MQ",
    "gn:dem":91,
    "gn:feature_class":"P",
    "gn:feature_code":"PPL",
    "gn:name":"Morne Vent\u00e9",
    "gn:population":0,
    "gn:timezone":"America/Martinique",
    "iso:country":"MQ",
    "wof:name":"Morne Vente",
    "wof:placetype":"locality"
},
  "geometry": {"coordinates":[-61.15,14.65],"type":"Point"}
}