{
  "type": "Feature",
  "properties": {
    "gn:admin1_code":"00",
    "gn:asciiname":"Dehaumont",
    "gn:country_code":"MQ",
    "gn:dem":31,
    "gn:feature_class":"P",
    "gn:feature_code":"PPL",
    "gn:name":"Dehaumont",
    "gn:population":0,
    "gn:timezone":"America/Martinique",
    "iso:country":"MQ",
    "name:fra_x_preferred":[
        "Dehaumont"
    ],
    "wof:name":"Dehaumont",
    "wof:placetype":"locality"
},
  "geometry": {"coordinates":[-61.03338000000001,14.82382],"type":"Point"}
}