{
  "type": "Feature",
  "properties": {
    "gn:admin1_code":"00",
    "gn:asciiname":"Providence",
    "gn:country_code":"MQ",
    "gn:dem":47,
    "gn:feature_class":"P",
    "gn:feature_code":"PPL",
    "gn:name":"Providence",
    "gn:population":0,
    "gn:timezone":"America/Martinique",
    "iso:country":"MQ",
    "name:fra_x_preferred":[
        "Providence"
    ],
    "wof:name":"Providence",
    "wof:placetype":"locality"
},
  "geometry": {"coordinates":[-60.93894,14.56377],"type":"Point"}
}