{
  "type": "Feature",
  "properties": {
    "gn:admin1_code":"00",
    "gn:asciiname":"Providence",
    "gn:country_code":"MQ",
    "gn:dem":47,
    "gn:feature_class":"P",
    "gn:feature_code":"PPL",
    "gn:name":"Providence",
    "gn:population":0,
    "gn:timezone":"America/Martinique",
    "iso:country":"MQ",
    "name:bel_x_preferred":[
        "\u041f\u0440\u043e\u0432\u0456\u0434\u044d\u043d\u0441"
    ],
    "name:bre_x_preferred":[
        "Providence"
    ],
    "name:cat_x_preferred":[
        "Providence"
    ],
    "name:ceb_x_preferred":[
        "Providence"
    ],
    "name:ces_x_preferred":[
        "Providence"
    ],
    "name:dan_x_preferred":[
        "Providence"
    ],
    "name:deu_x_preferred":[
        "Providence"
    ],
    "name:epo_x_preferred":[
        "Providenco"
    ],
    "name:fin_x_preferred":[
        "Providence"
    ],
    "name:fra_x_preferred":[
        "Providence"
    ],
    "name:hun_x_preferred":[
        "Providence"
    ],
    "name:ita_x_preferred":[
        "Providence"
    ],
    "name:jpn_x_preferred":[
        "\u30d7\u30ed\u30d3\u30c7\u30f3\u30b9"
    ],
    "name:kor_x_preferred":[
        "\ud504\ub85c\ube44\ub358\uc2a4"
    ],
    "name:nld_x_preferred":[
        "Providence"
    ],
    "name:oci_x_preferred":[
        "Providence"
    ],
    "name:pol_x_preferred":[
        "Providence"
    ],
    "name:por_x_preferred":[
        "Providence"
    ],
    "name:rus_x_preferred":[
        "\u041f\u0440\u043e\u0432\u0438\u0434\u0435\u043d\u0441"
    ],
    "name:sco_x_preferred":[
        "Providence"
    ],
    "name:slk_x_preferred":[
        "Providence"
    ],
    "name:spa_x_preferred":[
        "Providence"
    ],
    "name:srp_x_preferred":[
        "\u041f\u0440\u043e\u0432\u0438\u0434\u0435\u043d\u0441"
    ],
    "name:swe_x_preferred":[
        "Providence"
    ],
    "name:tur_x_preferred":[
        "Providence"
    ],
    "name:ukr_x_preferred":[
        "\u041f\u0440\u043e\u0432\u0456\u0434\u0435\u043d\u0441"
    ],
    "name:urd_x_preferred":[
        "\u067e\u0631\u0648\u0648\u06cc\u0688\u0646\u0633"
    ],
    "name:vol_x_preferred":[
        "Providence"
    ],
    "name:zho_x_preferred":[
        "\u666e\u7f57\u7ef4\u767b\u65af"
    ],
    "wof:name":"Providence",
    "wof:placetype":"locality"
},
  "geometry": {"coordinates":[-60.93894,14.56377],"type":"Point"}
}