{
  "type": "Feature",
  "properties": {
    "gn:admin1_code":"MQ",
    "gn:admin2_code":"972.0",
    "gn:admin3_code":"9723.0",
    "gn:admin4_code":"97231.0",
    "gn:asciiname":"Rateau",
    "gn:country_code":"MQ",
    "gn:dem":273,
    "gn:feature_class":"P",
    "gn:feature_code":"PPL",
    "gn:name":"Rateau",
    "gn:population":0,
    "gn:timezone":"America/Martinique",
    "iso:country":"MQ",
    "name:deu_x_preferred":[
        "Rateau"
    ],
    "name:fra_x_preferred":[
        "Rateau"
    ],
    "wof:name":"Rateau",
    "wof:placetype":"locality"
},
  "geometry": {"coordinates":[-61.02008000000001,14.51284],"type":"Point"}
}