{
  "type": "Feature",
  "properties": {
    "gn:admin1_code":"MQ",
    "gn:admin2_code":"972.0",
    "gn:admin3_code":"9722.0",
    "gn:admin4_code":"97228.0",
    "gn:asciiname":"Belle Etoile",
    "gn:country_code":"MQ",
    "gn:dem":101,
    "gn:feature_class":"P",
    "gn:feature_code":"PPL",
    "gn:name":"Belle \u00c9toile",
    "gn:population":0,
    "gn:timezone":"America/Martinique",
    "iso:country":"MQ",
    "name:und_x_variant":[
        "Quartier Belle-\u00c9toile",
        "Belle \u00c9toile"
    ],
    "wof:name":"Belle Etoile",
    "wof:placetype":"locality"
},
  "geometry": {"coordinates":[-60.98714,14.77098],"type":"Point"}
}