{
  "type": "Feature",
  "properties": {
    "gn:admin1_code":"00",
    "gn:asciiname":"Petit Galion",
    "gn:country_code":"MQ",
    "gn:dem":28,
    "gn:feature_class":"P",
    "gn:feature_code":"PPL",
    "gn:name":"Petit Galion",
    "gn:population":0,
    "gn:timezone":"America/Martinique",
    "iso:country":"MQ",
    "name:fra_x_preferred":[
        "Petit Galion"
    ],
    "wof:name":"Petit Galion",
    "wof:placetype":"locality"
},
  "geometry": {"coordinates":[-60.93802,14.70948],"type":"Point"}
}