{
  "type": "Feature",
  "properties": {
    "gn:admin1_code":"00",
    "gn:asciiname":"Delaine",
    "gn:country_code":"MQ",
    "gn:dem":19,
    "gn:feature_class":"P",
    "gn:feature_code":"PPLL",
    "gn:name":"Delaine",
    "gn:population":0,
    "gn:timezone":"America/Martinique",
    "iso:country":"MQ",
    "name:fra_x_preferred":[
        "Delaine"
    ],
    "wof:name":"Delaine",
    "wof:placetype":"locality"
},
  "geometry": {"coordinates":[-60.96908000000001,14.59559],"type":"Point"}
}