{
  "type": "Feature",
  "properties": {
    "gn:admin1_code":"00",
    "gn:asciiname":"Courbaril-Louisy",
    "gn:country_code":"MQ",
    "gn:dem":172,
    "gn:feature_class":"P",
    "gn:feature_code":"PPL",
    "gn:name":"Courbaril-Louisy",
    "gn:population":0,
    "gn:timezone":"America/Martinique",
    "iso:country":"MQ",
    "name:fra_x_preferred":[
        "Courbaril-Louisy"
    ],
    "wof:name":"Courbaril-Louisy",
    "wof:placetype":"locality"
},
  "geometry": {"coordinates":[-60.95219,14.50962],"type":"Point"}
}