{
  "type": "Feature",
  "properties": {
    "gn:admin1_code":"MQ",
    "gn:admin2_code":"972.0",
    "gn:admin3_code":"9721.0",
    "gn:admin4_code":"97224.0",
    "gn:asciiname":"La Durand",
    "gn:country_code":"MQ",
    "gn:dem":268,
    "gn:feature_class":"P",
    "gn:feature_code":"PPL",
    "gn:name":"La Durand",
    "gn:population":0,
    "gn:timezone":"America/Martinique",
    "iso:country":"MQ",
    "name:und_x_variant":[
        "Quartier Durand",
        "La Durand"
    ],
    "wof:name":"La Durand",
    "wof:placetype":"locality"
},
  "geometry": {"coordinates":[-61.05287,14.6829],"type":"Point"}
}