{
  "type": "Feature",
  "properties": {
    "gn:admin1_code":"00",
    "gn:asciiname":"Grand Boucan",
    "gn:country_code":"MQ",
    "gn:dem":228,
    "gn:feature_class":"P",
    "gn:feature_code":"PPL",
    "gn:name":"Grand Boucan",
    "gn:population":0,
    "gn:timezone":"America/Martinique",
    "iso:country":"MQ",
    "name:fra_x_preferred":[
        "Grand Boucan"
    ],
    "wof:name":"Grand Boucan",
    "wof:placetype":"locality"
},
  "geometry": {"coordinates":[-60.89331,14.56171],"type":"Point"}
}