{
  "type": "Feature",
  "properties": {
    "gn:admin1_code":"00",
    "gn:asciiname":"Felicite",
    "gn:country_code":"MQ",
    "gn:dem":117,
    "gn:feature_class":"P",
    "gn:feature_code":"PPL",
    "gn:name":"F\u00e9licit\u00e9",
    "gn:population":0,
    "gn:timezone":"America/Martinique",
    "iso:country":"MQ",
    "name:fra_x_preferred":[
        "F\u00e9licit\u00e9"
    ],
    "wof:name":"Felicite",
    "wof:placetype":"locality"
},
  "geometry": {"coordinates":[-60.99256999999999,14.77066],"type":"Point"}
}