{
  "type": "Feature",
  "properties": {
    "gn:admin1_code":"00",
    "gn:asciiname":"Sebastopol",
    "gn:country_code":"MQ",
    "gn:dem":17,
    "gn:feature_class":"P",
    "gn:feature_code":"PPLL",
    "gn:name":"S\u00e9bastopol",
    "gn:population":0,
    "gn:timezone":"America/Martinique",
    "iso:country":"MQ",
    "name:fra_x_preferred":[
        "S\u00e9bastopol"
    ],
    "wof:name":"Sebastopol",
    "wof:placetype":"locality"
},
  "geometry": {"coordinates":[-60.96389,14.59952],"type":"Point"}
}