{
  "type": "Feature",
  "properties": {
    "gn:admin1_code":"MQ",
    "gn:admin2_code":"972.0",
    "gn:admin3_code":"9723.0",
    "gn:admin4_code":"97226.0",
    "gn:asciiname":"Les Salines Dillon",
    "gn:country_code":"MQ",
    "gn:dem":15,
    "gn:feature_class":"P",
    "gn:feature_code":"PPL",
    "gn:name":"Les Salines Dillon",
    "gn:population":0,
    "gn:timezone":"America/Martinique",
    "iso:country":"MQ",
    "name:fra_x_preferred":[
        "Les Salines Dillon"
    ],
    "name:und_x_variant":[
        "Salines Dillon"
    ],
    "wof:name":"Les Salines Dillon",
    "wof:placetype":"locality"
},
  "geometry": {"coordinates":[-60.86538,14.41121],"type":"Point"}
}