{
  "type": "Feature",
  "properties": {
    "gn:admin1_code":"00",
    "gn:asciiname":"La Bananeraie",
    "gn:country_code":"MQ",
    "gn:dem":19,
    "gn:feature_class":"P",
    "gn:feature_code":"PPLL",
    "gn:name":"La Bananeraie",
    "gn:population":0,
    "gn:timezone":"America/Martinique",
    "iso:country":"MQ",
    "name:fra_x_preferred":[
        "La Bananeraie"
    ],
    "wof:name":"La Bananeraie",
    "wof:placetype":"locality"
},
  "geometry": {"coordinates":[-60.99463000000001,14.63412],"type":"Point"}
}