{
  "type": "Feature",
  "properties": {
    "gn:admin1_code":"MQ",
    "gn:admin2_code":"972.0",
    "gn:admin3_code":"9722.0",
    "gn:admin4_code":"97228.0",
    "gn:asciiname":"Pain de Sucre",
    "gn:country_code":"MQ",
    "gn:dem":103,
    "gn:feature_class":"P",
    "gn:feature_code":"PPL",
    "gn:name":"Pain de Sucre",
    "gn:population":0,
    "gn:timezone":"America/Martinique",
    "iso:country":"MQ",
    "name:fra_x_preferred":[
        "Pain de Sucre"
    ],
    "wof:name":"Pain de Sucre",
    "wof:placetype":"locality"
},
  "geometry": {"coordinates":[-61.00921,14.80437],"type":"Point"}
}