{
  "type": "Feature",
  "properties": {
    "gn:admin1_code":"00",
    "gn:asciiname":"La Montagne",
    "gn:country_code":"MQ",
    "gn:dem":206,
    "gn:feature_class":"P",
    "gn:feature_code":"PPL",
    "gn:name":"La Montagne",
    "gn:population":0,
    "gn:timezone":"America/Martinique",
    "iso:country":"MQ",
    "name:fra_x_preferred":[
        "La Montagne"
    ],
    "wof:name":"La Montagne",
    "wof:placetype":"locality"
},
  "geometry": {"coordinates":[-60.87166,14.55586],"type":"Point"}
}