{
  "type": "Feature",
  "properties": {
    "gn:admin1_code":"MQ",
    "gn:admin2_code":"972.0",
    "gn:admin3_code":"9723.0",
    "gn:admin4_code":"97206.0",
    "gn:asciiname":"Dizac",
    "gn:country_code":"MQ",
    "gn:dem":18,
    "gn:feature_class":"P",
    "gn:feature_code":"PPL",
    "gn:name":"Dizac",
    "gn:population":0,
    "gn:timezone":"America/Martinique",
    "iso:country":"MQ",
    "name:fra_x_preferred":[
        "Dizac"
    ],
    "wof:name":"Dizac",
    "wof:placetype":"locality"
},
  "geometry": {"coordinates":[-61.03331,14.47985],"type":"Point"}
}