{
  "type": "Feature",
  "properties": {
    "gn:admin1_code":"MQ",
    "gn:admin2_code":"972.0",
    "gn:admin3_code":"9722.0",
    "gn:admin4_code":"97230.0",
    "gn:asciiname":"Balata",
    "gn:country_code":"MQ",
    "gn:dem":17,
    "gn:feature_class":"P",
    "gn:feature_code":"PPL",
    "gn:name":"Balata",
    "gn:population":0,
    "gn:timezone":"America/Martinique",
    "iso:country":"MQ",
    "name:fra_x_preferred":[
        "Balata"
    ],
    "wof:name":"Balata",
    "wof:placetype":"locality"
},
  "geometry": {"coordinates":[-60.89791999999999,14.75945],"type":"Point"}
}