{
  "type": "Feature",
  "properties": {
    "gn:admin1_code":"MQ",
    "gn:admin2_code":"972.0",
    "gn:admin3_code":"9723.0",
    "gn:admin4_code":"97210.0",
    "gn:asciiname":"La Gillot",
    "gn:country_code":"MQ",
    "gn:dem":183,
    "gn:feature_class":"P",
    "gn:feature_code":"PPL",
    "gn:name":"La Gillot",
    "gn:population":0,
    "gn:timezone":"America/Martinique",
    "iso:country":"MQ",
    "name:fra_x_preferred":[
        "La Gillot"
    ],
    "name:und_x_variant":[
        "Quartier Gillot"
    ],
    "wof:name":"La Gillot",
    "wof:placetype":"locality"
},
  "geometry": {"coordinates":[-60.90039,14.58632],"type":"Point"}
}