{
  "type": "Feature",
  "properties": {
    "gn:admin1_code":"MQ",
    "gn:admin2_code":"972.0",
    "gn:admin3_code":"9723.0",
    "gn:admin4_code":"97221.0",
    "gn:asciiname":"Courbaril",
    "gn:country_code":"MQ",
    "gn:dem":67,
    "gn:feature_class":"P",
    "gn:feature_code":"PPL",
    "gn:name":"Courbaril",
    "gn:population":0,
    "gn:timezone":"America/Martinique",
    "iso:country":"MQ",
    "name:und_x_variant":[
        "Quartier Courbaril"
    ],
    "wof:name":"Courbaril",
    "wof:placetype":"locality"
},
  "geometry": {"coordinates":[-60.94841,14.54743],"type":"Point"}
}