{
  "type": "Feature",
  "properties": {
    "gn:admin1_code":"00",
    "gn:asciiname":"La Cherry",
    "gn:country_code":"MQ",
    "gn:dem":11,
    "gn:feature_class":"P",
    "gn:feature_code":"PPL",
    "gn:name":"La Cherry",
    "gn:population":0,
    "gn:timezone":"America/Martinique",
    "iso:country":"MQ",
    "name:fra_x_preferred":[
        "La Cherry"
    ],
    "wof:name":"La Cherry",
    "wof:placetype":"locality"
},
  "geometry": {"coordinates":[-61.00764,14.47655],"type":"Point"}
}