{
  "type": "Feature",
  "properties": {
    "gn:admin1_code":"00",
    "gn:asciiname":"Corneille",
    "gn:country_code":"MQ",
    "gn:dem":155,
    "gn:feature_class":"P",
    "gn:feature_code":"PPL",
    "gn:name":"Corneille",
    "gn:population":0,
    "gn:timezone":"America/Martinique",
    "iso:country":"MQ",
    "name:fra_x_preferred":[
        "Corneille"
    ],
    "wof:name":"Corneille",
    "wof:placetype":"locality"
},
  "geometry": {"coordinates":[-61.01944,14.70372],"type":"Point"}
}