{
  "type": "Feature",
  "properties": {
    "gn:admin1_code":"MQ",
    "gn:admin2_code":"972.0",
    "gn:admin3_code":"9724.0",
    "gn:admin4_code":"97218.0",
    "gn:asciiname":"Petite Savane",
    "gn:country_code":"MQ",
    "gn:dem":533,
    "gn:feature_class":"P",
    "gn:feature_code":"PPL",
    "gn:name":"Petite Savane",
    "gn:population":0,
    "gn:timezone":"America/Martinique",
    "iso:country":"MQ",
    "name:und_x_variant":[
        "Quartier Petite Savane",
        "Petite Savane"
    ],
    "wof:name":"Petite Savane",
    "wof:placetype":"locality"
},
  "geometry": {"coordinates":[-61.13762,14.79093],"type":"Point"}
}