{
  "type": "Feature",
  "properties": {
    "gn:admin1_code":"00",
    "gn:asciiname":"Duchatel",
    "gn:country_code":"MQ",
    "gn:dem":60,
    "gn:feature_class":"P",
    "gn:feature_code":"PPL",
    "gn:name":"Duch\u00e2tel",
    "gn:population":0,
    "gn:timezone":"America/Martinique",
    "iso:country":"MQ",
    "name:fra_x_preferred":[
        "Duch\u00e2tel"
    ],
    "wof:name":"Duchatel",
    "wof:placetype":"locality"
},
  "geometry": {"coordinates":[-60.93459,14.57997],"type":"Point"}
}