{
  "type": "Feature",
  "properties": {
    "gn:admin1_code":"00",
    "gn:asciiname":"Case Jules",
    "gn:country_code":"MQ",
    "gn:dem":9,
    "gn:feature_class":"P",
    "gn:feature_code":"PPL",
    "gn:name":"Case Jules",
    "gn:population":0,
    "gn:timezone":"America/Martinique",
    "iso:country":"MQ",
    "name:fra_x_preferred":[
        "Case Jules"
    ],
    "wof:name":"Case Jules",
    "wof:placetype":"locality"
},
  "geometry": {"coordinates":[-61.00029,14.77873],"type":"Point"}
}