{
  "type": "Feature",
  "properties": {
    "gn:admin1_code":"MQ",
    "gn:admin2_code":"972.0",
    "gn:admin3_code":"9721.0",
    "gn:admin4_code":"97209.0",
    "gn:asciiname":"La Medaille",
    "gn:country_code":"MQ",
    "gn:dem":499,
    "gn:feature_class":"P",
    "gn:feature_code":"PPL",
    "gn:name":"La M\u00e9daille",
    "gn:population":0,
    "gn:timezone":"America/Martinique",
    "iso:country":"MQ",
    "name:und_x_variant":[
        "Quartier la M\u00e9daille",
        "Medaille",
        "La M\u00e9daille"
    ],
    "wof:name":"La Medaille",
    "wof:placetype":"locality"
},
  "geometry": {"coordinates":[-61.08859,14.70162],"type":"Point"}
}