{
  "type": "Feature",
  "properties": {
    "gn:admin1_code":"00",
    "gn:asciiname":"Quartier Reservoir",
    "gn:country_code":"MQ",
    "gn:dem":101,
    "gn:feature_class":"P",
    "gn:feature_code":"PPL",
    "gn:name":"Quartier R\u00e9servoir",
    "gn:population":0,
    "gn:timezone":"America/Martinique",
    "iso:country":"MQ",
    "name:fra_x_preferred":[
        "Quartier R\u00e9servoir"
    ],
    "wof:name":"Quartier Reservoir",
    "wof:placetype":"locality"
},
  "geometry": {"coordinates":[-60.88614000000001,14.52538],"type":"Point"}
}