{
  "type": "Feature",
  "properties": {
    "gn:admin1_code":"MQ",
    "gn:admin2_code":"972.0",
    "gn:admin3_code":"9722.0",
    "gn:admin4_code":"97216.0",
    "gn:asciiname":"Morne Bois",
    "gn:country_code":"MQ",
    "gn:dem":207,
    "gn:feature_class":"P",
    "gn:feature_code":"PPL",
    "gn:name":"Morne Bois",
    "gn:population":0,
    "gn:timezone":"America/Martinique",
    "iso:country":"MQ",
    "name:und_x_variant":[
        "Quartier Morne Bois",
        "Morne Bois"
    ],
    "wof:name":"Morne Bois",
    "wof:placetype":"locality"
},
  "geometry": {"coordinates":[-61.05602,14.81232],"type":"Point"}
}