{
  "type": "Feature",
  "properties": {
    "gn:admin1_code":"MQ",
    "gn:asciiname":"Marie Noire",
    "gn:country_code":"MQ",
    "gn:dem":47,
    "gn:feature_class":"P",
    "gn:feature_code":"PPL",
    "gn:name":"Marie Noire",
    "gn:population":0,
    "gn:timezone":"America/Martinique",
    "iso:country":"MQ",
    "name:fra_x_preferred":[
        "Marie Noire"
    ],
    "wof:name":"Marie Noire",
    "wof:placetype":"locality"
},
  "geometry": {"coordinates":[-60.90161,14.46935],"type":"Point"}
}