{
  "type": "Feature",
  "properties": {
    "gn:admin1_code":"00",
    "gn:asciiname":"La Pointe des Sables",
    "gn:country_code":"MQ",
    "gn:dem":13,
    "gn:feature_class":"P",
    "gn:feature_code":"PPL",
    "gn:name":"La Pointe des Sables",
    "gn:population":0,
    "gn:timezone":"America/Martinique",
    "iso:country":"MQ",
    "name:fra_x_preferred":[
        "La Pointe des Sables"
    ],
    "wof:name":"La Pointe des Sables",
    "wof:placetype":"locality"
},
  "geometry": {"coordinates":[-60.84824,14.57864],"type":"Point"}
}