{
  "type": "Feature",
  "properties": {
    "gn:admin1_code":"00",
    "gn:asciiname":"Thoraille",
    "gn:country_code":"MQ",
    "gn:dem":64,
    "gn:feature_class":"P",
    "gn:feature_code":"PPL",
    "gn:name":"Thoraille",
    "gn:population":0,
    "gn:timezone":"America/Martinique",
    "iso:country":"MQ",
    "name:fra_x_preferred":[
        "Thoraille"
    ],
    "wof:name":"Thoraille",
    "wof:placetype":"locality"
},
  "geometry": {"coordinates":[-61.02461,14.49022],"type":"Point"}
}