{
  "type": "Feature",
  "properties": {
    "gn:admin1_code":"MQ",
    "gn:admin2_code":"972.0",
    "gn:admin3_code":"9721.0",
    "gn:admin4_code":"97213.0",
    "gn:asciiname":"Beleme",
    "gn:country_code":"MQ",
    "gn:dem":114,
    "gn:feature_class":"P",
    "gn:feature_code":"PPL",
    "gn:name":"B\u00e9l\u00e8me",
    "gn:population":0,
    "gn:timezone":"America/Martinique",
    "iso:country":"MQ",
    "name:fra_x_preferred":[
        "B\u00e9l\u00e8me"
    ],
    "name:und_x_variant":[
        "Quartier la Bellem",
        "Quartier la Belem",
        "Quartier la B\u00e9l\u00e8me",
        "La Bel\u00e8me"
    ],
    "wof:name":"Beleme",
    "wof:placetype":"locality"
},
  "geometry": {"coordinates":[-61.00906,14.65157],"type":"Point"}
}