{
  "type": "Feature",
  "properties": {
    "gn:admin1_code":"MQ",
    "gn:admin2_code":"972.0",
    "gn:admin3_code":"9723.0",
    "gn:admin4_code":"97210.0",
    "gn:asciiname":"Baldara",
    "gn:country_code":"MQ",
    "gn:dem":169,
    "gn:feature_class":"P",
    "gn:feature_code":"PPL",
    "gn:name":"Baldara",
    "gn:population":0,
    "gn:timezone":"America/Martinique",
    "iso:country":"MQ",
    "name:fra_x_preferred":[
        "Baldara"
    ],
    "name:hin_x_preferred":[
        "\u092c\u093e\u0932\u0926\u0921\u093c\u093e"
    ],
    "name:und_x_variant":[
        "Quartier Morne Baldara",
        "Morne Baldara"
    ],
    "wof:name":"Baldara",
    "wof:placetype":"locality"
},
  "geometry": {"coordinates":[-60.90465,14.56967],"type":"Point"}
}