{
  "type": "Feature",
  "properties": {
    "gn:admin1_code":"00",
    "gn:asciiname":"Riviere Blanche",
    "gn:country_code":"MQ",
    "gn:dem":104,
    "gn:feature_class":"P",
    "gn:feature_code":"PPL",
    "gn:name":"Rivi\u00e8re Blanche",
    "gn:population":0,
    "gn:timezone":"America/Martinique",
    "iso:country":"MQ",
    "name:fra_x_preferred":[
        "Rivi\u00e8re Blanche"
    ],
    "wof:name":"Riviere Blanche",
    "wof:placetype":"locality"
},
  "geometry": {"coordinates":[-61.01006,14.67663],"type":"Point"}
}