{
  "type": "Feature",
  "properties": {
    "gn:admin1_code":"00",
    "gn:asciiname":"Fourniols",
    "gn:country_code":"MQ",
    "gn:dem":86,
    "gn:feature_class":"P",
    "gn:feature_code":"PPL",
    "gn:name":"Fourniols",
    "gn:population":0,
    "gn:timezone":"America/Martinique",
    "iso:country":"MQ",
    "name:fra_x_preferred":[
        "Fourniols"
    ],
    "wof:name":"Fourniols",
    "wof:placetype":"locality"
},
  "geometry": {"coordinates":[-61.00867,14.77042],"type":"Point"}
}