{
  "type": "Feature",
  "properties": {
    "gn:admin1_code":"00",
    "gn:asciiname":"Bassin Dames",
    "gn:country_code":"MQ",
    "gn:dem":113,
    "gn:feature_class":"P",
    "gn:feature_code":"PPL",
    "gn:name":"Bassin Dames",
    "gn:population":0,
    "gn:timezone":"America/Martinique",
    "iso:country":"MQ",
    "name:fra_x_preferred":[
        "Bassin Dames"
    ],
    "wof:name":"Bassin Dames",
    "wof:placetype":"locality"
},
  "geometry": {"coordinates":[-60.92393000000001,14.48048],"type":"Point"}
}