{
  "type": "Feature",
  "properties": {
    "gn:admin1_code":"MQ",
    "gn:admin2_code":"972.0",
    "gn:admin3_code":"9721.0",
    "gn:admin4_code":"97224.0",
    "gn:asciiname":"Fond Cacao",
    "gn:country_code":"MQ",
    "gn:dem":155,
    "gn:feature_class":"P",
    "gn:feature_code":"PPL",
    "gn:name":"Fond Cacao",
    "gn:population":0,
    "gn:timezone":"America/Martinique",
    "iso:country":"MQ",
    "name:und_x_variant":[
        "Quartier Fond Cacao",
        "Fond Cacao"
    ],
    "wof:name":"Fond Cacao",
    "wof:placetype":"locality"
},
  "geometry": {"coordinates":[-61.03605,14.66155],"type":"Point"}
}