{
  "type": "Feature",
  "properties": {
    "gn:admin1_code":"MQ",
    "gn:admin2_code":"972.0",
    "gn:admin3_code":"9721.0",
    "gn:admin4_code":"97213.0",
    "gn:asciiname":"Lareinty",
    "gn:country_code":"MQ",
    "gn:dem":13,
    "gn:feature_class":"P",
    "gn:feature_code":"PPL",
    "gn:name":"Lareinty",
    "gn:population":0,
    "gn:timezone":"America/Martinique",
    "iso:country":"MQ",
    "name:und_x_variant":[
        "Marly",
        "Lareinty"
    ],
    "wof:name":"Lareinty",
    "wof:placetype":"locality"
},
  "geometry": {"coordinates":[-60.99536,14.5984],"type":"Point"}
}