{
  "type": "Feature",
  "properties": {
    "gn:admin1_code":"MQ",
    "gn:admin2_code":"972.0",
    "gn:admin3_code":"9721.0",
    "gn:admin4_code":"97213.0",
    "gn:asciiname":"La Cadet",
    "gn:country_code":"MQ",
    "gn:dem":59,
    "gn:feature_class":"P",
    "gn:feature_code":"PPL",
    "gn:name":"La Cadet",
    "gn:population":0,
    "gn:timezone":"America/Martinique",
    "iso:country":"MQ",
    "name:fra_x_preferred":[
        "La Cadet"
    ],
    "name:und_x_variant":[
        "Cadet"
    ],
    "wof:name":"La Cadet",
    "wof:placetype":"locality"
},
  "geometry": {"coordinates":[-60.97286999999999,14.66476],"type":"Point"}
}