{
  "type": "Feature",
  "properties": {
    "gn:admin1_code":"MQ",
    "gn:admin2_code":"972.0",
    "gn:admin3_code":"9723.0",
    "gn:admin4_code":"97223.0",
    "gn:asciiname":"Laboissiere",
    "gn:country_code":"MQ",
    "gn:dem":261,
    "gn:feature_class":"P",
    "gn:feature_code":"PPL",
    "gn:name":"Laboissi\u00e8re",
    "gn:population":0,
    "gn:timezone":"America/Martinique",
    "iso:country":"MQ",
    "name:fra_x_preferred":[
        "Laboissi\u00e8re"
    ],
    "name:und_x_variant":[
        "Quartier la Boissi\u00e8re",
        "La Boissi\u00e8re"
    ],
    "wof:name":"Laboissiere",
    "wof:placetype":"locality"
},
  "geometry": {"coordinates":[-60.89871,14.5512],"type":"Point"}
}