{
  "type": "Feature",
  "properties": {
    "gn:admin1_code":"00",
    "gn:asciiname":"Beola",
    "gn:country_code":"MQ",
    "gn:dem":123,
    "gn:feature_class":"P",
    "gn:feature_code":"PPL",
    "gn:name":"B\u00e9ola",
    "gn:population":0,
    "gn:timezone":"America/Martinique",
    "iso:country":"MQ",
    "name:fra_x_preferred":[
        "B\u00e9ola"
    ],
    "wof:name":"Beola",
    "wof:placetype":"locality"
},
  "geometry": {"coordinates":[-60.94936,14.4966],"type":"Point"}
}