{
  "type": "Feature",
  "properties": {
    "gn:admin1_code":"00",
    "gn:asciiname":"Gaigneron",
    "gn:country_code":"MQ",
    "gn:dem":11,
    "gn:feature_class":"P",
    "gn:feature_code":"PPL",
    "gn:name":"Gaigneron",
    "gn:population":0,
    "gn:timezone":"America/Martinique",
    "iso:country":"MQ",
    "name:fra_x_preferred":[
        "Gaigneron"
    ],
    "wof:name":"Gaigneron",
    "wof:placetype":"locality"
},
  "geometry": {"coordinates":[-60.99627,14.60302],"type":"Point"}
}