{
  "type": "Feature",
  "properties": {
    "gn:admin1_code":"MQ",
    "gn:admin2_code":"972.0",
    "gn:admin3_code":"9723.0",
    "gn:admin4_code":"97210.0",
    "gn:asciiname":"Grands Fonds",
    "gn:country_code":"MQ",
    "gn:dem":13,
    "gn:feature_class":"P",
    "gn:feature_code":"PPL",
    "gn:name":"Grands Fonds",
    "gn:population":0,
    "gn:timezone":"America/Martinique",
    "iso:country":"MQ",
    "name:fra_x_preferred":[
        "Grands Fonds"
    ],
    "name:und_x_variant":[
        "Grand Fonds",
        "Grand Fond"
    ],
    "wof:name":"Grands Fonds",
    "wof:placetype":"locality"
},
  "geometry": {"coordinates":[-60.92536,14.61759],"type":"Point"}
}