{
  "type": "Feature",
  "properties": {
    "gn:admin1_code":"MQ",
    "gn:admin2_code":"972.0",
    "gn:admin3_code":"9722.0",
    "gn:admin4_code":"97212.0",
    "gn:asciiname":"Dumaine",
    "gn:country_code":"MQ",
    "gn:dem":251,
    "gn:feature_class":"P",
    "gn:feature_code":"PPL",
    "gn:name":"Dumaine",
    "gn:population":0,
    "gn:timezone":"America/Martinique",
    "iso:country":"MQ",
    "name:und_x_variant":[
        "Quartier Dumaine",
        "Dumaine"
    ],
    "wof:name":"Dumaine",
    "wof:placetype":"locality"
},
  "geometry": {"coordinates":[-61.01985,14.72099],"type":"Point"}
}