{
  "type": "Feature",
  "properties": {
    "gn:admin1_code":"00",
    "gn:asciiname":"Morne Degras",
    "gn:country_code":"MQ",
    "gn:dem":139,
    "gn:feature_class":"P",
    "gn:feature_code":"PPL",
    "gn:name":"Morne Degras",
    "gn:population":0,
    "gn:timezone":"America/Martinique",
    "iso:country":"MQ",
    "name:fra_x_preferred":[
        "Morne Degras"
    ],
    "wof:name":"Morne Degras",
    "wof:placetype":"locality"
},
  "geometry": {"coordinates":[-60.92691,14.54631],"type":"Point"}
}