{
  "type": "Feature",
  "properties": {
    "gn:admin1_code":"00",
    "gn:asciiname":"Riviere la Manche",
    "gn:country_code":"MQ",
    "gn:dem":21,
    "gn:feature_class":"P",
    "gn:feature_code":"PPL",
    "gn:name":"Rivi\u00e8re la Manche",
    "gn:population":0,
    "gn:timezone":"America/Martinique",
    "iso:country":"MQ",
    "name:fra_x_preferred":[
        "Rivi\u00e8re la Manche"
    ],
    "name:fra_x_variant":[
        "La Rouchy"
    ],
    "wof:name":"Riviere la Manche",
    "wof:placetype":"locality"
},
  "geometry": {"coordinates":[-60.96518,14.56515],"type":"Point"}
}