{
  "type": "Feature",
  "properties": {
    "gn:admin1_code":"00",
    "gn:asciiname":"Saintonge",
    "gn:country_code":"MQ",
    "gn:dem":225,
    "gn:feature_class":"P",
    "gn:feature_code":"PPL",
    "gn:name":"Saintonge",
    "gn:population":0,
    "gn:timezone":"America/Martinique",
    "iso:country":"MQ",
    "name:bel_x_preferred":[
        "\u0421\u0435\u043d\u0442\u043e\u043d\u0436"
    ],
    "name:bre_x_preferred":[
        "Saintonge"
    ],
    "name:cat_x_preferred":[
        "Saintonge"
    ],
    "name:cym_x_preferred":[
        "Saintonge"
    ],
    "name:deu_x_preferred":[
        "Saintonge"
    ],
    "name:ell_x_preferred":[
        "\u03a3\u03b1\u03b9\u03bd\u03c4\u03cc\u03bd\u03b6"
    ],
    "name:epo_x_preferred":[
        "Santon\u011do"
    ],
    "name:eus_x_preferred":[
        "Saintonge"
    ],
    "name:fra_x_preferred":[
        "Saintonge"
    ],
    "name:glg_x_preferred":[
        "Saintonge"
    ],
    "name:ita_x_preferred":[
        "Saintonge"
    ],
    "name:nld_x_preferred":[
        "Saintonge"
    ],
    "name:oci_x_preferred":[
        "Santonge"
    ],
    "name:pol_x_preferred":[
        "Saintonge"
    ],
    "name:rus_x_preferred":[
        "\u0421\u0435\u043d\u0442\u043e\u043d\u0436"
    ],
    "name:slv_x_preferred":[
        "Saintonge"
    ],
    "name:spa_x_preferred":[
        "Saintonge"
    ],
    "name:swe_x_preferred":[
        "Saintonge"
    ],
    "name:ukr_x_preferred":[
        "\u0421\u0435\u043d\u0442\u043e\u043d\u0436"
    ],
    "name:urd_x_preferred":[
        "\u0633\u06cc\u0646\u0679\u0648\u0646\u06af\u06d2"
    ],
    "wof:name":"Saintonge",
    "wof:placetype":"locality"
},
  "geometry": {"coordinates":[-60.89094,14.48655],"type":"Point"}
}