{
  "type": "Feature",
  "properties": {
    "gn:admin1_code":"00",
    "gn:asciiname":"Saintonge",
    "gn:country_code":"MQ",
    "gn:dem":225,
    "gn:feature_class":"P",
    "gn:feature_code":"PPL",
    "gn:name":"Saintonge",
    "gn:population":0,
    "gn:timezone":"America/Martinique",
    "iso:country":"MQ",
    "name:fra_x_preferred":[
        "Saintonge"
    ],
    "wof:name":"Saintonge",
    "wof:placetype":"locality"
},
  "geometry": {"coordinates":[-60.89094,14.48655],"type":"Point"}
}