{
  "type": "Feature",
  "properties": {
    "gn:admin1_code":"MQ",
    "gn:admin2_code":"972.0",
    "gn:admin3_code":"9723.0",
    "gn:admin4_code":"97223.0",
    "gn:asciiname":"Palmene",
    "gn:country_code":"MQ",
    "gn:dem":87,
    "gn:feature_class":"P",
    "gn:feature_code":"PPL",
    "gn:name":"Palm\u00e8ne",
    "gn:population":0,
    "gn:timezone":"America/Martinique",
    "iso:country":"MQ",
    "name:fra_x_preferred":[
        "Palm\u00e8ne"
    ],
    "name:und_x_variant":[
        "Quartier Palm\u00e8ne"
    ],
    "wof:name":"Palmene",
    "wof:placetype":"locality"
},
  "geometry": {"coordinates":[-60.91401,14.55835],"type":"Point"}
}