{
  "type": "Feature",
  "properties": {
    "gn:admin1_code":"MQ",
    "gn:admin2_code":"972.0",
    "gn:admin3_code":"9721.0",
    "gn:admin4_code":"97213.0",
    "gn:asciiname":"Belfort",
    "gn:country_code":"MQ",
    "gn:dem":98,
    "gn:feature_class":"P",
    "gn:feature_code":"PPL",
    "gn:name":"Belfort",
    "gn:population":0,
    "gn:timezone":"America/Martinique",
    "iso:country":"MQ",
    "name:und_x_variant":[
        "Quartier Belfort",
        "Belfort"
    ],
    "wof:name":"Belfort",
    "wof:placetype":"locality"
},
  "geometry": {"coordinates":[-61.00489,14.65124],"type":"Point"}
}