{
  "type": "Feature",
  "properties": {
    "gn:admin1_code":"MQ",
    "gn:admin2_code":"972.0",
    "gn:admin3_code":"9721.0",
    "gn:admin4_code":"97213.0",
    "gn:asciiname":"Riviere Calecon",
    "gn:country_code":"MQ",
    "gn:dem":57,
    "gn:feature_class":"P",
    "gn:feature_code":"PPL",
    "gn:name":"Rivi\u00e8re Cale\u00e7on",
    "gn:population":0,
    "gn:timezone":"America/Martinique",
    "iso:country":"MQ",
    "name:und_x_variant":[
        "Quartier Rivi\u00e8re Cale\u00e7on",
        "Rivi\u00e8re Cale\u00e7on"
    ],
    "wof:name":"Riviere Calecon",
    "wof:placetype":"locality"
},
  "geometry": {"coordinates":[-60.96357,14.6174],"type":"Point"}
}