{
  "type": "Feature",
  "properties": {
    "gn:admin1_code":"MQ",
    "gn:admin2_code":"972.0",
    "gn:admin3_code":"9723.0",
    "gn:admin4_code":"97221.0",
    "gn:asciiname":"Ravine Chien",
    "gn:country_code":"MQ",
    "gn:dem":77,
    "gn:feature_class":"P",
    "gn:feature_code":"PPL",
    "gn:name":"Ravine Chien",
    "gn:population":0,
    "gn:timezone":"America/Martinique",
    "iso:country":"MQ",
    "name:fra_x_preferred":[
        "Ravine Chien"
    ],
    "name:und_x_variant":[
        "Ravine-Chien"
    ],
    "wof:name":"Ravine Chien",
    "wof:placetype":"locality"
},
  "geometry": {"coordinates":[-60.94796,14.53073],"type":"Point"}
}