{
  "type": "Feature",
  "properties": {
    "gn:admin1_code":"00",
    "gn:asciiname":"L'Union",
    "gn:country_code":"MQ",
    "gn:dem":43,
    "gn:feature_class":"P",
    "gn:feature_code":"PPL",
    "gn:name":"L\u2019Union",
    "gn:population":0,
    "gn:timezone":"America/Martinique",
    "iso:country":"MQ",
    "name:fra_x_preferred":[
        "L\u2019Union"
    ],
    "wof:name":"L'Union",
    "wof:placetype":"locality"
},
  "geometry": {"coordinates":[-60.8686,14.56555],"type":"Point"}
}