{
  "type": "Feature",
  "properties": {
    "gn:admin1_code":"00",
    "gn:asciiname":"La Deslande",
    "gn:country_code":"MQ",
    "gn:dem":14,
    "gn:feature_class":"P",
    "gn:feature_code":"PPL",
    "gn:name":"La Deslande",
    "gn:population":0,
    "gn:timezone":"America/Martinique",
    "iso:country":"MQ",
    "name:fra_x_preferred":[
        "La Deslande"
    ],
    "wof:name":"La Deslande",
    "wof:placetype":"locality"
},
  "geometry": {"coordinates":[-61.00119,14.52809],"type":"Point"}
}