{
  "type": "Feature",
  "properties": {
    "gn:admin1_code":"MQ",
    "gn:admin2_code":"972.0",
    "gn:admin3_code":"9723.0",
    "gn:admin4_code":"97226.0",
    "gn:asciiname":"Macre",
    "gn:country_code":"MQ",
    "gn:dem":90,
    "gn:feature_class":"P",
    "gn:feature_code":"PPL",
    "gn:name":"Macr\u00e9",
    "gn:population":0,
    "gn:timezone":"America/Martinique",
    "iso:country":"MQ",
    "name:fra_x_preferred":[
        "Macr\u00e9"
    ],
    "wof:name":"Macre",
    "wof:placetype":"locality"
},
  "geometry": {"coordinates":[-60.83278000000001,14.47714],"type":"Point"}
}