{
  "type": "Feature",
  "properties": {
    "gn:admin1_code":"00",
    "gn:asciiname":"Les Ravinieres",
    "gn:country_code":"MQ",
    "gn:dem":35,
    "gn:feature_class":"P",
    "gn:feature_code":"PPL",
    "gn:name":"Les Ravini\u00e8res",
    "gn:population":0,
    "gn:timezone":"America/Martinique",
    "iso:country":"MQ",
    "name:fra_x_preferred":[
        "Les Ravini\u00e8res"
    ],
    "wof:name":"Les Ravinieres",
    "wof:placetype":"locality"
},
  "geometry": {"coordinates":[-60.93178,14.56801],"type":"Point"}
}