{
  "type": "Feature",
  "properties": {
    "gn:admin1_code":"MQ",
    "gn:asciiname":"Pointe Fort",
    "gn:country_code":"MQ",
    "gn:dem":-9999,
    "gn:feature_class":"P",
    "gn:feature_code":"PPLL",
    "gn:name":"Pointe Fort",
    "gn:population":0,
    "gn:timezone":"America/Martinique",
    "iso:country":"MQ",
    "wof:name":"Pointe Fort",
    "wof:placetype":"locality"
},
  "geometry": {"coordinates":[-60.91667,14.66667],"type":"Point"}
}