{
  "type": "Feature",
  "properties": {
    "gn:admin1_code":"00",
    "gn:asciiname":"Plaisance",
    "gn:country_code":"MQ",
    "gn:dem":187,
    "gn:feature_class":"P",
    "gn:feature_code":"PPL",
    "gn:name":"Plaisance",
    "gn:population":0,
    "gn:timezone":"America/Martinique",
    "iso:country":"MQ",
    "name:fra_x_preferred":[
        "Plaisance"
    ],
    "wof:name":"Plaisance",
    "wof:placetype":"locality"
},
  "geometry": {"coordinates":[-61.02063,14.78324],"type":"Point"}
}