{
  "type": "Feature",
  "properties": {
    "gn:admin1_code":"00",
    "gn:asciiname":"Plaisance",
    "gn:country_code":"MQ",
    "gn:dem":187,
    "gn:feature_class":"P",
    "gn:feature_code":"PPL",
    "gn:name":"Plaisance",
    "gn:population":0,
    "gn:timezone":"America/Martinique",
    "iso:country":"MQ",
    "name:cat_x_preferred":[
        "Plaisance"
    ],
    "name:ceb_x_preferred":[
        "Plaisance"
    ],
    "name:deu_x_preferred":[
        "Plaisance"
    ],
    "name:fas_x_preferred":[
        "\u067e\u0644\u0633\u0627\u0646\u0633"
    ],
    "name:fra_x_preferred":[
        "Plaisance"
    ],
    "name:heb_x_preferred":[
        "\u05e4\u05dc\u05d0\u05d9\u05e1\u05d0\u05e0\u05e1"
    ],
    "name:hun_x_preferred":[
        "Plaisance"
    ],
    "name:ita_x_preferred":[
        "Plaisance"
    ],
    "name:nds_x_preferred":[
        "Plaisance"
    ],
    "name:nld_x_preferred":[
        "Plaisance"
    ],
    "name:pms_x_preferred":[
        "Plaisance"
    ],
    "name:pol_x_preferred":[
        "Plaisance"
    ],
    "name:por_x_preferred":[
        "Plaisance"
    ],
    "name:rus_x_preferred":[
        "\u041f\u043b\u0435\u0437\u0430\u043d\u0441"
    ],
    "name:slk_x_preferred":[
        "Plaisance"
    ],
    "name:spa_x_preferred":[
        "Plaisance"
    ],
    "name:swe_x_preferred":[
        "Plaisance"
    ],
    "name:ukr_x_preferred":[
        "\u041f\u043b\u0435\u0437\u0430\u043d\u0441"
    ],
    "wof:name":"Plaisance",
    "wof:placetype":"locality"
},
  "geometry": {"coordinates":[-61.02063,14.78324],"type":"Point"}
}