{
  "type": "Feature",
  "properties": {
    "gn:admin1_code":"MQ",
    "gn:admin2_code":"972.0",
    "gn:admin3_code":"9722.0",
    "gn:admin4_code":"97203.0",
    "gn:asciiname":"Morne Balai",
    "gn:country_code":"MQ",
    "gn:dem":329,
    "gn:feature_class":"P",
    "gn:feature_code":"PPL",
    "gn:name":"Morne Balai",
    "gn:population":0,
    "gn:timezone":"America/Martinique",
    "iso:country":"MQ",
    "name:fra_x_preferred":[
        "Morne Balai"
    ],
    "name:und_x_variant":[
        "Quartier Morne Balai",
        "Morne-Balai"
    ],
    "wof:name":"Morne Balai",
    "wof:placetype":"locality"
},
  "geometry": {"coordinates":[-61.12841,14.83179],"type":"Point"}
}