{
  "type": "Feature",
  "properties": {
    "gn:admin1_code":"MQ",
    "gn:admin2_code":"972.0",
    "gn:admin3_code":"9724.0",
    "gn:admin4_code":"97234.0",
    "gn:asciiname":"Verrier",
    "gn:country_code":"MQ",
    "gn:dem":536,
    "gn:feature_class":"P",
    "gn:feature_code":"PPL",
    "gn:name":"Verrier",
    "gn:population":0,
    "gn:timezone":"America/Martinique",
    "iso:country":"MQ",
    "name:und_x_variant":[
        "Quartier Verrier",
        "Verrier"
    ],
    "wof:name":"Verrier",
    "wof:placetype":"locality"
},
  "geometry": {"coordinates":[-61.14084,14.68712],"type":"Point"}
}