{
  "type": "Feature",
  "properties": {
    "gn:admin1_code":"00",
    "gn:asciiname":"Bitaille",
    "gn:country_code":"MQ",
    "gn:dem":145,
    "gn:feature_class":"P",
    "gn:feature_code":"PPL",
    "gn:name":"Bitaille",
    "gn:population":0,
    "gn:timezone":"America/Martinique",
    "iso:country":"MQ",
    "name:fra_x_preferred":[
        "Bitaille"
    ],
    "wof:name":"Bitaille",
    "wof:placetype":"locality"
},
  "geometry": {"coordinates":[-61.00864,14.49997],"type":"Point"}
}