{
  "type": "Feature",
  "properties": {
    "gn:admin1_code":"00",
    "gn:asciiname":"La Cour",
    "gn:country_code":"MQ",
    "gn:dem":225,
    "gn:feature_class":"P",
    "gn:feature_code":"PPLL",
    "gn:name":"La Cour",
    "gn:population":0,
    "gn:timezone":"America/Martinique",
    "iso:country":"MQ",
    "name:fra_x_preferred":[
        "La Cour"
    ],
    "wof:name":"La Cour",
    "wof:placetype":"locality"
},
  "geometry": {"coordinates":[-61.02302,14.7591],"type":"Point"}
}