{
  "type": "Feature",
  "properties": {
    "gn:admin1_code":"00",
    "gn:asciiname":"La Source",
    "gn:country_code":"MQ",
    "gn:dem":180,
    "gn:feature_class":"P",
    "gn:feature_code":"PPL",
    "gn:name":"La Source",
    "gn:population":0,
    "gn:timezone":"America/Martinique",
    "iso:country":"MQ",
    "name:ceb_x_preferred":[
        "La Source"
    ],
    "name:fra_x_preferred":[
        "La Source"
    ],
    "name:pol_x_preferred":[
        "La Source"
    ],
    "name:spa_x_preferred":[
        "La Source"
    ],
    "name:swe_x_preferred":[
        "La Source"
    ],
    "wof:name":"La Source",
    "wof:placetype":"locality"
},
  "geometry": {"coordinates":[-60.98875,14.70692],"type":"Point"}
}