{
  "type": "Feature",
  "properties": {
    "gn:admin1_code":"00",
    "gn:asciiname":"Bellevue-Union",
    "gn:country_code":"MQ",
    "gn:dem":24,
    "gn:feature_class":"P",
    "gn:feature_code":"PPL",
    "gn:name":"Bellevue-Union",
    "gn:population":0,
    "gn:timezone":"America/Martinique",
    "iso:country":"MQ",
    "name:fra_x_preferred":[
        "Bellevue-Union"
    ],
    "wof:name":"Bellevue-Union",
    "wof:placetype":"locality"
},
  "geometry": {"coordinates":[-61.00682,14.78403],"type":"Point"}
}