{
  "type": "Feature",
  "properties": {
    "gn:admin1_code":"MQ",
    "gn:admin2_code":"972.0",
    "gn:admin3_code":"9722.0",
    "gn:admin4_code":"97230.0",
    "gn:asciiname":"Merveilleuse",
    "gn:country_code":"MQ",
    "gn:dem":87,
    "gn:feature_class":"P",
    "gn:feature_code":"PPL",
    "gn:name":"Merveilleuse",
    "gn:population":0,
    "gn:timezone":"America/Martinique",
    "iso:country":"MQ",
    "name:fra_x_preferred":[
        "Merveilleuse"
    ],
    "wof:name":"Merveilleuse",
    "wof:placetype":"locality"
},
  "geometry": {"coordinates":[-60.97902,14.75383],"type":"Point"}
}