{
  "type": "Feature",
  "properties": {
    "gn:admin1_code":"MQ",
    "gn:admin2_code":"972.0",
    "gn:admin3_code":"9721.0",
    "gn:admin4_code":"97213.0",
    "gn:asciiname":"Bois Carre",
    "gn:country_code":"MQ",
    "gn:dem":25,
    "gn:feature_class":"P",
    "gn:feature_code":"PPL",
    "gn:name":"Bois Carr\u00e9",
    "gn:population":0,
    "gn:timezone":"America/Martinique",
    "iso:country":"MQ",
    "name:fra_x_preferred":[
        "Bois Carr\u00e9"
    ],
    "wof:name":"Bois Carre",
    "wof:placetype":"locality"
},
  "geometry": {"coordinates":[-60.99306,14.62967],"type":"Point"}
}