{
  "type": "Feature",
  "properties": {
    "gn:admin1_code":"MQ",
    "gn:admin2_code":"972.0",
    "gn:admin3_code":"9721.0",
    "gn:admin4_code":"97213.0",
    "gn:asciiname":"Boutaud",
    "gn:country_code":"MQ",
    "gn:dem":124,
    "gn:feature_class":"P",
    "gn:feature_code":"PPL",
    "gn:name":"Boutaud",
    "gn:population":0,
    "gn:timezone":"America/Martinique",
    "iso:country":"MQ",
    "name:und_x_variant":[
        "Quartier Boutaud",
        "Quartier la Boutaud",
        "Boutaud"
    ],
    "wof:name":"Boutaud",
    "wof:placetype":"locality"
},
  "geometry": {"coordinates":[-60.97318000000001,14.67588],"type":"Point"}
}