{
  "type": "Feature",
  "properties": {
    "gn:admin1_code":"00",
    "gn:asciiname":"Fonds Abricot",
    "gn:country_code":"MQ",
    "gn:dem":210,
    "gn:feature_class":"P",
    "gn:feature_code":"PPL",
    "gn:name":"Fonds Abricot",
    "gn:population":0,
    "gn:timezone":"America/Martinique",
    "iso:country":"MQ",
    "name:fra_x_preferred":[
        "Fonds Abricot"
    ],
    "wof:name":"Fonds Abricot",
    "wof:placetype":"locality"
},
  "geometry": {"coordinates":[-61.00938000000001,14.69649],"type":"Point"}
}