{
  "type": "Feature",
  "properties": {
    "gn:admin1_code":"00",
    "gn:asciiname":"Toknay",
    "gn:country_code":"MQ",
    "gn:dem":220,
    "gn:feature_class":"P",
    "gn:feature_code":"PPL",
    "gn:name":"Toknay",
    "gn:population":0,
    "gn:timezone":"America/Martinique",
    "iso:country":"MQ",
    "name:fra_x_preferred":[
        "Toknay"
    ],
    "wof:name":"Toknay",
    "wof:placetype":"locality"
},
  "geometry": {"coordinates":[-60.94057,14.47812],"type":"Point"}
}