{
  "type": "Feature",
  "properties": {
    "gn:admin1_code":"00",
    "gn:asciiname":"Quamalon",
    "gn:country_code":"MQ",
    "gn:dem":171,
    "gn:feature_class":"P",
    "gn:feature_code":"PPL",
    "gn:name":"Quamalon",
    "gn:population":0,
    "gn:timezone":"America/Martinique",
    "iso:country":"MQ",
    "name:fra_x_preferred":[
        "Quamalon"
    ],
    "wof:name":"Quamalon",
    "wof:placetype":"locality"
},
  "geometry": {"coordinates":[-61.05589000000001,14.48516],"type":"Point"}
}