{
  "type": "Feature",
  "properties": {
    "gn:admin1_code":"MQ",
    "gn:admin2_code":"972.0",
    "gn:admin3_code":"9723.0",
    "gn:admin4_code":"97210.0",
    "gn:asciiname":"Belle Ame",
    "gn:country_code":"MQ",
    "gn:dem":150,
    "gn:feature_class":"P",
    "gn:feature_code":"PPL",
    "gn:name":"Belle \u00c2me",
    "gn:population":0,
    "gn:timezone":"America/Martinique",
    "iso:country":"MQ",
    "name:und_x_variant":[
        "Quartier Belle \u00c2me",
        "Belle \u00c2me"
    ],
    "wof:name":"Belle Ame",
    "wof:placetype":"locality"
},
  "geometry": {"coordinates":[-60.94103000000001,14.62981],"type":"Point"}
}