{
  "type": "Feature",
  "properties": {
    "gn:admin1_code":"MQ",
    "gn:admin2_code":"972.0",
    "gn:admin3_code":"9724.0",
    "gn:admin4_code":"97218.0",
    "gn:asciiname":"Fond Marie-Reine",
    "gn:country_code":"MQ",
    "gn:dem":354,
    "gn:feature_class":"P",
    "gn:feature_code":"PPL",
    "gn:name":"Fond Marie-Reine",
    "gn:population":0,
    "gn:timezone":"America/Martinique",
    "iso:country":"MQ",
    "name:und_x_variant":[
        "Quartier Fond Marie Reine",
        "Fond Marie-Reine"
    ],
    "wof:name":"Fond Marie-Reine",
    "wof:placetype":"locality"
},
  "geometry": {"coordinates":[-61.12371,14.76507],"type":"Point"}
}