{
  "type": "Feature",
  "properties": {
    "gn:admin1_code":"MQ",
    "gn:admin2_code":"972.0",
    "gn:admin3_code":"9723.0",
    "gn:admin4_code":"97226.0",
    "gn:asciiname":"Morne Pois",
    "gn:country_code":"MQ",
    "gn:dem":47,
    "gn:feature_class":"P",
    "gn:feature_code":"PPL",
    "gn:name":"Morne Pois",
    "gn:population":0,
    "gn:timezone":"America/Martinique",
    "iso:country":"MQ",
    "name:fra_x_preferred":[
        "Morne Pois"
    ],
    "wof:name":"Morne Pois",
    "wof:placetype":"locality"
},
  "geometry": {"coordinates":[-60.85915,14.43979],"type":"Point"}
}