{
  "type": "Feature",
  "properties": {
    "gn:admin1_code":"MQ",
    "gn:admin2_code":"972.0",
    "gn:admin3_code":"9723.0",
    "gn:admin4_code":"97210.0",
    "gn:asciiname":"Saint-Laurent",
    "gn:country_code":"MQ",
    "gn:dem":68,
    "gn:feature_class":"P",
    "gn:feature_code":"PPL",
    "gn:name":"Saint-Laurent",
    "gn:population":0,
    "gn:timezone":"America/Martinique",
    "iso:country":"MQ",
    "name:fra_x_preferred":[
        "Saint-Laurent"
    ],
    "wof:name":"Saint-Laurent",
    "wof:placetype":"locality"
},
  "geometry": {"coordinates":[-60.92146,14.58803],"type":"Point"}
}